Workbook

Sheet About
A1: Seven Elements of ZTA — ZPA requirements matrix
A2: Built 2026-10-20. Every requirement the book places on private application access, mapped to the Private Access (ZPA) capability that meets it and the help.zscaler.com article that documents it.
A4: Document
A5: Type / scope / status | B5: reference · general, with tenant-specific project notes (as in reference/glossary.md) · draft
A6: Updated | B6: 2026-10-20
A7: Sources | B7: The book (below) and every article on the ‘Help articles’ sheet, each read on the date shown there.
A9: Source
A10: Book | B10: Seven Elements of Highly Successful Zero Trust Architecture — An Architect’s Guide to the Zscaler Zero Trust Exchange. Nathan Howe, Sanjit Ganguli, Gerard Festa. Third edition, January 2024. ISBN 979-8-9871864-1-1.
A11: File | B11: reference/seven-elements-of-highly-successful-zta.pdf (154 PDF pages). Printed page = PDF page − 2.
A12: Nature of the source | B12: Vendor-authored. Its requirements are framed around Zscaler’s own architecture, so a high ‘Native’ count is expected and is not independent evidence of fitness for this estate. Use the matrix as a checklist of design principles and a map to the docs, not as an evaluation.
A14: Method
A15: Extraction | B15: All 154 pages read. A row is a requirement the book places on private (internal) application access, or on the platform where ZPA must meet it. Statements repeated across elements are consolidated into one row with every page that states them. Pro tips and recommendations are kept as Type = Guidance.
A16: Book basis | B16: Verbatim quotes, each checked by script against the PDF text layer; the page columns are generated from where each quote occurs plus other pages that restate the same requirement.
A17: Help articles | B17: Every cited article was opened and read on 2026-10-20. help.zscaler.com is a JavaScript application, so pages were rendered (not fetched raw) and the canonical URL after redirects is recorded. The evidence column quotes the article verbatim. Where no article supports a requirement, the row says so rather than citing a near miss.
A18: Naming | B18: The help centre now titles the product ‘Private Access (ZPA)’ and the console the ‘Zscaler Admin Console’; this matrix uses the current names. Some features the book describes have been renamed or extended since January 2024.
A19: Out of scope | B19: Book requirements that belong to other Zscaler products (Internet & SaaS/ZIA, ZDX, CASB, Posture Control) are listed on the ‘Not ZPA’ sheet for completeness, without help articles.
A21: Fit legend
A22: Native | B22: A Private Access (ZPA) capability meets the requirement as the book states it.
A23: Partial | B23: ZPA meets part of it; the rest needs design work, another component, or is not documented. The ‘How ZPA meets it’ column names the gap.
A24: Other Zscaler product | B24: Met by a Zscaler product outside ZPA that integrates with ZPA policy or traffic (Branch/Cloud Connector, Deception, Microsegmentation, Internet & SaaS risk scoring). Usually a separate licence.
A25: Dependency | B25: Met outside Zscaler (IdP, EDR, the customer’s own classification); ZPA consumes the result.
A26: Gap | B26: No ZPA capability found in the help centre. Absence from the docs is evidence, not proof — confirm with Zscaler before designing around it.
A27: Not in help centre | B27: Commercial or assurance property (SLA, tenancy); evidence comes from contract or assurance documents, not the help centre.
A29: Columns worth knowing
A30: Project note | B30: Tenant-specific. Facts recorded in this repo (README, decisions, discovery, backlog, glossary) with their reference, or a statement explicitly labelled Inferred / Open. Blank means the repo records nothing that bears on the row.
A31: Constraints | B31: Only what the cited article states (licences, prerequisites, limited availability). Blank means none stated in the article read — not that none exist.
A32: Fit | B32: Drop-down. Edit it as the design firms up; the Summary sheet recounts.
A34: Counts
A35: Requirement rows | B35: =COUNTA(Requirements!A2:A70) -> 69
A36: Rows not met by ZPA (Not ZPA sheet) | B36: =COUNTA('Not ZPA'!A2:A24) -> 23
A37: Help articles cited | B37: =COUNTA('Help articles'!A2:A98) -> 97

Sheet Requirements
A1: ID | B1: Book section | C1: Theme | D1: Type | E1: Requirement (normalised from the book) | F1: Book basis (verbatim) | G1: Book pages (printed) | H1: PDF pages | I1: ZPA feature / capability | J1: How ZPA meets it | K1: Fit | L1: Primary help article | M1: Primary article URL | N1: Supporting help articles | O1: Help-centre evidence (verbatim) | P1: Constraints / prerequisites stated in the docs | Q1: Project note (this estate) | R1: Article verified
A2: ZT-01 | B2: Overview of zero trust | C2: Architecture | D2: Requirement | E2: Grant no implicit trust from network location or asset ownership: access is granted only after identity and context are verified and policy is enforced (least privilege). | F2: “trust is only granted once identity and context are verified and policy checks are enforced” | G2: 11, 27 | H2: 13, 29 | I2: Brokered user-to-application access; implicit block in access policy | J2: ZPA never grants network access: a user reaches only the applications an access policy rule allows, after IdP authentication through Client Connector. With no matching rule, access is implicitly blocked. | K2: Native | L2: What Is Zscaler Private Access? | M2: https://help.zscaler.com/zpa/what-zscaler-private-access | N2: Understanding Policies — https://help.zscaler.com/zpa/understanding-policies Understanding the Private Access Architecture — https://help.zscaler.com/zpa/understanding-private-access-architecture | O2: [What Is Zscaler Private Access?] “With Private Access, application access does not require network access.” [Understanding Policies] “For access policy, access to the application is implicitly set to Block Access. This is also the case if you do not define any policy rules at all within the Zscaler Admin Console.” | Q2: README objective: ‘No user or workload can reach a service it has no policy for.’ The workload half is deferred: east-west is out of scope (decision 2026-09-19). | R2: 2026-10-20
A3: ZT-02 | B3: Overview of zero trust | C3: Architecture | D3: Requirement | E3: Private applications must be invisible to unauthorised initiators: not exposed to the internet or to connected networks, and not discoverable (no services, FQDNs or IPs) until policy permits access. | F3: “Apps are invisible (sit behind Zscaler controls) and can’t be discovered from unauthorized sources (internet or connected networks)” “for private apps–cannot even see that the requested application exists” | G3: 12, 52, 116, 124, 133, 145 | H3: 14, 54, 118, 126, 135, 147 | I3: App Connectors (outbound-only) behind the Service Edge broker | J3: Applications sit behind App Connectors that only dial out to a Public or Private Service Edge, so nothing about the app is published to the internet through ZPA, and Zscaler describes apps as invisible and unroutable to all but authorised users. ZPA does not remove other routes to the app (LAN, cloud public IPs) — those must be closed separately for the invisibility claim to hold. | K3: Partial | L3: What Is Zscaler Private Access? | M3: https://help.zscaler.com/zpa/what-zscaler-private-access | N3: About App Connectors — https://help.zscaler.com/zpa/about-connectors Understanding the Private Access Architecture — https://help.zscaler.com/zpa/understanding-private-access-architecture Private Service Edge Deployment Prerequisites — https://help.zscaler.com/zpa/service-edge-deployment-prerequisites | O3: [What Is Zscaler Private Access?] “Private Access renders your applications invisible to all but the authorized users and unroutable to anyone.” [About App Connectors] “App Connectors only connect outbound; they do not need any inbound open ports to operate correctly.” | P3: [Private Service Edge Deployment Prerequisites] “Your firewalls must be configured to let the Private Service Edge establish outbound connections to the IP addresses of the Public Service Edge for Private Access, and establish inbound connections from App Connectors and Zscaler Client Connector.” | Q3: current-state.md: Azure/AWS-hosted apps may already be reachable directly from the internet; a ZPA segment hides nothing unless that path is closed too. See also ZT-59 — on the LAN, invisibility holds only where direct routes are closed. | R3: 2026-10-20
A4: ZT-03 | B4: Overview of zero trust | C4: Segmentation | D4: Requirement | E4: Connect a specific authorised user to a specific authorised application, never to the network, so there is no routable path for lateral movement. | F4: “Connects a specific, authorized user to a specific, authorized resource” “users are given access not to networks, but to applications” | G4: 12, 124, 133, 145 | H4: 14, 126, 135, 147 | I4: Application segments + access policy (per-application brokering) | J4: Client Connector sends only traffic for defined application segments to Private Access (other traffic goes to Internet & SaaS or direct), and access policy decides which segments a user may reach. No network-level access is granted. | K4: Native | L4: What Is Zscaler Private Access? | M4: https://help.zscaler.com/zpa/what-zscaler-private-access | N4: Understanding the Private Access Architecture — https://help.zscaler.com/zpa/understanding-private-access-architecture About Access Policy — https://help.zscaler.com/zpa/about-access-policy | O4: [What Is Zscaler Private Access?] “With Private Access, application access does not require network access.” [Understanding the Private Access Architecture] “Zscaler Client Connector identifies internal applications to forward traffic to Private Access, and other traffic goes to Internet & SaaS.” | Q4: For a load-balanced app ZPA brokers user → VIP only; VIP → pool member and server-to-server legs keep today’s reachability (decision 2026-09-19; glossary ‘Virtual IP’). | R4: 2026-10-20
A5: ZT-04 | B5: Overview of zero trust | C5: Segmentation | D5: Requirement | E5: Enforce user-to-application segmentation through identity-aware policy that is independent of network segmentation (VLANs, subnets, firewall rules); the network is transport only. | F5: “not reliant on rigid network segmentation” “User-to-application segmentation can therefore be achieved not based on cumbersome network controls but rather by identity-aware policies.” | G5: 11, 18, 51, 124, 126 | H5: 13, 20, 53, 126, 128 | I5: Access policy on identity criteria (SAML/SCIM attributes, SCIM groups) against segments and segment groups | J5: Rules are written against who the user is (IdP attributes and groups) and which application segments or segment groups they may use — role-based access control — not against source subnets or VLANs. | K5: Native | L5: About Access Policy | M5: https://help.zscaler.com/zpa/about-access-policy | N5: Configuring Access Policies — https://help.zscaler.com/zpa/configuring-access-policies About SAML Attributes — https://help.zscaler.com/zpa/about-saml-attributes | O5: [About Access Policy] “Access policy rules enable you to implement role-based access control. To configure an access policy rule, you must first define the users and then define which applications or segment groups they can access.” | P5: [Configuring Access Policies] “In order for Private Access to process SAML and SCIM criteria in a rule, you must enable the SAML Attributes for Policy setting for SAML and the SCIM Attributes and Groups for Policy setting for SCIM when configuring an IdP.” | Q5: README: reachability by identity + posture, not source IP or VLAN. Glossary ‘ACL’: an app enforcing its own source-IP ACL sees the App Connector’s address, so it stops distinguishing users — for every user at once, at cutover. | R5: 2026-10-20
A6: ZT-05 | B6: Overview of zero trust | C6: Third-party & B2B | D6: Requirement | E6: Give third parties and B2B partners (contractors, suppliers, customers, users outside the primary authentication domain) application-level access under the same identity-based policy, without network access, and treat them as a separate risk population from employees. | F6: “third-party access, workload-to-workload, and location-to-location segmentation” “Validated external user (not part of primary auth domain)” | G6: 18, 37, 44, 74, 129, 148 | H6: 20, 39, 46, 76, 131, 150 | I6: B2B Federation; multiple IdPs; Browser Access and PRA for third parties | J6: Two documented models. (1) Third-party users sign in through an IdP the tenant trusts (up to 10 IdP configurations) and get application-level access policy like employees. (2) B2B Federation: a host tenant shares hostname-based segments with a guest partner’s ZPA tenant; guest users sign in with their own IdP via Client Connector, and only the guest admin writes the access policy for shared apps (the host sees it read-only). Browser Access and PRA give contractors clientless options. | K6: Native | L6: Understanding Business-to-Business (B2B) Federation | M6: https://help.zscaler.com/zpa/understanding-business-business-b2b-federation | N6: Configuring an IdP for Single Sign-On — https://help.zscaler.com/zpa/configuring-idp-single-sign About Browser Access — https://help.zscaler.com/zpa/about-browser-access Understanding Privileged Remote Access — https://help.zscaler.com/zpa/understanding-privileged-remote-access | O6: [Understanding Business-to-Business (B2B) Federation] “The user authenticates into Zscaler Client Connector using their standard corporate (guest tenant) credentials. Zscaler Client Connector authentication is always tied to the guest partner's IdP.” [Understanding Business-to-Business (B2B) Federation] “Only the guest partner admin can define, configure, and modify access policies to allow guest partners access to the shared host partner applications. The host partner has read-only access to view the policies configured by the guest partner.” [Configuring an IdP for Single Sign-On] “Within the Zscaler Admin Console, you can add up to 10 IdP configurations for single sign-on (SSO).” | P6: [Understanding Business-to-Business (B2B) Federation] “This feature is in limited availability, and requires a Private Access (ZPA) Federation license.” [Understanding Business-to-Business (B2B) Federation] “Both the host and guest partners must originate from the same cloud.” [Understanding Business-to-Business (B2B) Federation] “B2B Federation supports only user-to-application access between two partners using Zscaler Client Connector.” [Understanding Business-to-Business (B2B) Federation] “Only application segments with hostname-based configurations can be federated.” | Q6: Network 2 (Entra-only) needs ‘federated Zscaler B2B access’ to ~10 AD-authenticating core apps (current-state.md); ruling: each must be uplifted to modern auth (decision 2026-09-27); ZPA must still identify network 2 users (T-059). If that means ZPA B2B Federation: both tenants on the same Zscaler cloud, hostname-based segments only, Client Connector only, and the network 2 admin writes the access policy for shared apps (help article). | R6: 2026-10-20
A7: ZT-06 | B7: Connecting to the Zero Trust Exchange | C7: Connectivity | D7: Requirement | E7: Provide an endpoint agent that maintains a persistent control plane and dynamic, per-application data-plane tunnels for internal applications, and is the same single agent used for internet/SaaS traffic. | F7: “persistent control plane and dynamic, microsegmented data plane tunnels to the Zero Trust Exchange for the purpose of internal app protection” | G7: 23, 136 | H7: 25, 138 | I7: Zscaler Client Connector (one agent for Internet & SaaS and Private Access) | J7: Client Connector carries Internet & SaaS and Private Access traffic from one agent; its forwarding profile sets how ZPA traffic is treated per network type, and it identifies internal applications to forward to Private Access. | K7: Native | L7: What Is Zscaler Client Connector? | M7: https://help.zscaler.com/zscaler-client-connector/what-is-zscaler-client-connector | N7: Configuring Forwarding Profiles for Zscaler Client Connector — https://help.zscaler.com/zscaler-client-connector/configuring-forwarding-profiles-zscaler-client-connector Understanding the Private Access Architecture — https://help.zscaler.com/zpa/understanding-private-access-architecture | O7: [What Is Zscaler Client Connector?] “Using Zscaler Client Connector, users can get all of the benefits of the Zscaler service for internet traffic, as well as granular, policy-based access to internal resources from a single point.” [Configuring Forwarding Profiles for Zscaler Client Connector] “The forwarding profile tells Zscaler Client Connector how to treat traffic from your users' systems in different network environments for the Internet & SaaS and Private Access services.” | P7: [What Is Zscaler Client Connector?] “If you are using the app for Private Access, your organization must use SAML authentication.” | Q7: Browser Access is out of scope, so every ZPA user needs Client Connector on an enrolled device (decision 2026-09-27). | R7: 2026-10-20
A8: ZT-07 | B8: Connecting to the Zero Trust Exchange | C8: Connectivity | D8: Requirement | E8: Where an agent cannot be installed (servers, IoT/OT, whole sites, cloud workloads), forward traffic into the platform from the site or cloud (GRE/IPsec, branch or cloud connector form factors). | F8: “customers can leverage site-based forwarding options (GRE or IPSEC tunnels) to connect entire sites to the Zero Trust Exchange” | G8: 23, 46, 137, 146, 148 | H8: 25, 48, 139, 148, 150 | I8: Branch Connector and Cloud Connector forwarding into Private Access; their groups as policy criteria | J8: Branch Connector (sites) and Cloud Connector (cloud workloads) are VMs that forward traffic to Internet & SaaS and Private Access; Branch/Cloud Connector groups and client types can be matched in access policy. The articles read do not mention IoT. | K8: Other Zscaler product | L8: About Branch Connectors | M8: https://help.zscaler.com/zpa/about-branch-connectors | N8: About Cloud Connectors — https://help.zscaler.com/zpa/about-cloud-connectors About Branch Connector Groups — https://help.zscaler.com/zpa/about-branch-connector-groups About Cloud Connector Groups — https://help.zscaler.com/zpa/about-cloud-connector-groups About Access Policy — https://help.zscaler.com/zpa/about-access-policy Understanding Business Continuity — https://help.zscaler.com/zpa/understanding-business-continuity | O8: [About Branch Connectors] “Branch Connectors are virtual machine (VM) images that simplify traffic forwarding to Zscaler services (i.e., Internet & SaaS (ZIA) and Private Access (ZPA)) without using shared server software.” [About Cloud Connectors] “Secure workload traffic to the internet and provide seamless connectivity to private applications in other cloud regions or data centers.” | P8: [Understanding Business Continuity] “Browser Access, Source IP Anchoring, Cloud Connector, and Branch Connector client types are not supported.” (Business Continuity mode — see ZT-64.) | Q8: Glossary: Branch Connector and Cloud Connector are not part of ZPA and are licensed separately; they are the documented routes for traffic with no Client Connector (servers, IoT, OT, payment terminals). Branch Connector’s Direct action leaves no ZPA record. EFTPOS may not tolerate brokering and may use IP literals (current-state.md; T-016). | R8: 2026-10-20
A9: ZT-08 | B9: Connecting to the Zero Trust Exchange | C9: Clientless & privileged access | D9: Requirement | E9: Give unmanaged devices that cannot run an agent clientless access through a protected portal reached by DNS CNAME, after IdP authentication, without direct interaction with the application. | F9: “DNS CNAME redirects traffic to a protected, private portal. Users then authenticate against an IdP to access web, RDP-based, and SSH-based applications.” | G9: 23, 43, 44 | H9: 25, 45, 46 | I9: Browser Access (web apps), Privileged Remote Access (RDP/SSH/VNC), user portal | J9: Browser Access delivers HTTP/HTTPS applications to a TLS 1.2 browser with no Client Connector, using a published CNAME and certificate per application; PRA covers RDP, SSH and VNC from the browser; a user portal lists the apps a user is allowed. | K9: Native | L9: About Browser Access | M9: https://help.zscaler.com/zpa/about-browser-access | N9: Understanding Privileged Remote Access — https://help.zscaler.com/zpa/understanding-privileged-remote-access Accessing a User Portal — https://help.zscaler.com/zpa/accessing-user-portal Configuring Defined Application Segments — https://help.zscaler.com/zpa/configuring-defined-application-segments About Applications — https://help.zscaler.com/zpa/about-applications | O9: [About Browser Access] “Browser Access allows you to leverage a web browser for user authentication and application access over Private Access (ZPA), without requiring users to install Zscaler Client Connector on their devices.” [About Browser Access] “Private Access supports HTTP and HTTPS protocols, and Private Access inserts a Via header in HTTP requests.” | P9: [About Browser Access] “Browser Access requires that the application server supports TLS 1.2 encryption.” [Configuring Defined Application Segments] “When defining applications for Browser Access, you can only configure FQDNs.” [About Applications] “Apply advanced capabilities that you are licensed for such as Browser Access, Zero Trust Browser, AppProtection, and data loss prevention.” | Q9: Out of scope: Browser Access is not enabled and no segment may use it (decision 2026-09-27). Unmanaged and partner-managed devices therefore have no ZPA path. | R9: 2026-10-20
A10: ZT-09 | B10: Connecting to the Zero Trust Exchange | C10: Connectivity | D10: Requirement | E10: Work over any underlying network, IPv4 or IPv6. | F10: “The network can be located anywhere and be built on IPv4 or IPv6” | G10: 22 | H10: 24 | I10: IPv4 and IPv6 support | J10: IPv4 is supported for TCP, UDP and ICMP. IPv6 applications are supported for TCP only; an IPv6 client reaching an IPv4 application works for TCP, UDP and ICMP. | K10: Partial | L10: Configuring IPv6 | M10: https://help.zscaler.com/zpa/configuring-ipv6 | N10: About App Connector Groups — https://help.zscaler.com/zpa/about-connector-groups | O10: [Configuring IPv6] “Private Access (ZPA) supports IPv4 for TCP-, UDP-, and ICMP-based connections, and supports IPv6 for only TCP-based applications.” [Configuring IPv6] “An IPv6 endpoint through Zscaler Client Connector to access an IPv4 application on the server is supported for TCP-, UDP-, and ICMP-based connections.” | P10: [Configuring IPv6] “Only TCP-based connections are supported for direct IPv6 communications from an App Connector to a server. UDP-based connections are not supported.” | R10: 2026-10-20
A11: ZT-10 | B11: Element 1 — Who is connecting? | C11: Identity | D11: Requirement | E11: Integrate with the enterprise IdP using standards (SAML; SCIM; OAuth named): the access service validates identity issued by the IdP rather than being the identity store. | F11: “a zero trust solution must have established integration with the enterprise IdP provider” “the zero trust solution is not the store of identity” | G11: 28, 29, 30, 32, 146 | H11: 30, 31, 32, 34, 148 | I11: IdP configuration (SAML 2.0, SP-initiated SSO); up to 10 IdPs; optional SCIM | J11: Users authenticate into Client Connector through any SAML 2.0 IdP (SP-initiated). ZPA keeps no hosted user database for SAML-only users — attributes travel in the SAML assertion; enabling SCIM adds provisioned users and groups. The book’s OAuth path has no counterpart in the ZPA user-IdP articles (OIDC appears only via Authentication Service — ZT-12). | K11: Native | L11: About IdP Configuration | M11: https://help.zscaler.com/zpa/about-idp-configuration | N11: Configuring an IdP for Single Sign-On — https://help.zscaler.com/zpa/configuring-idp-single-sign About SAML Attributes — https://help.zscaler.com/zpa/about-saml-attributes | O11: [About IdP Configuration] “For users to access your applications via Private Access (ZPA), they must first authenticate into Zscaler Client Connector using any SAML 2.0-compliant identity provider (IdP) with the service provider-initiated (SP initiated) model.” [About SAML Attributes] “Private Access does not use a hosted user database for provisioning, so user attributes within SAML assertions cannot be viewed within the Zscaler Admin Console.” | P11: [About IdP Configuration] “The IdP Configuration page is read only if you are subscribed to Authentication Service for users.” [Configuring an IdP for Single Sign-On] “If you update an IdP certificate, this change triggers an Authentication Error message in the Zscaler Client Connector for users and prevents access to your apps.” | Q11: Identity is split — Entra ID and on-prem AD, one-way AD → Entra sync (current-state.md). Inferred: the IdP ZPA authenticates against decides which attributes policy can use. | R11: 2026-10-20
A12: ZT-11 | B12: Element 1 — Who is connecting? | C12: Identity | D12: Requirement | E12: Receive identity changes from the IdP after login (provisioning, deprovisioning, group membership), not only the authentication result. | F12: “receive updates on changes to that verification” | G12: 30, 32 | H12: 32, 34 | I12: SCIM 2.0 provisioning of users, groups and attributes | J12: With SCIM enabled, disabling or deleting a user in the directory removes them from Private Access, and SCIM groups and attributes become policy criteria. What happens to sessions already open is not documented, and SAML-attribute changes apply only after the user re-authenticates. | K12: Native | L12: About SCIM | M12: https://help.zscaler.com/zpa/about-scim | N12: About SCIM Groups — https://help.zscaler.com/zpa/about-scim-groups Deleting Users in SCIM — https://help.zscaler.com/zpa/deleting-users-scim SCIM Configuration Guide for Microsoft Azure AD — https://help.zscaler.com/zpa/scim-configuration-guide-microsoft-azure-ad Configuring Timeout Policies — https://help.zscaler.com/zpa/configuring-timeout-policies | O12: [About SCIM] “Enabling SCIM allows the Zero Trust Exchange (ZTE) to quickly remove users from Private Access when a user is disabled or deleted in your user directory and to enforce policies based on SCIM attributes and SCIM groups.” [Configuring Timeout Policies] “In addition, if a configuration change is made on an IdP that also causes a change to the SAML assertion, then the updated assertion is applied to Private Access (ZPA) policies after the user reauthenticates.” | P12: [Deleting Users in SCIM] “Users accessing applications via Browser Access can not be removed from Private Access using SCIM.” [About SCIM] “Zscaler only supports SCIM version 2.0.” [SCIM Configuration Guide for Microsoft Azure AD] “After SCIM Sync is enabled, Zscaler recommends waiting a minimum of 48 hours, or up to a week, before enabling SCIM policies.” | Q12: backlog T-053: the onboarding triage search separates a SCIM sync gap from posture and DNS failures — provisioning lag surfaces as a failed first session. | R12: 2026-10-20
A13: ZT-12 | B13: Element 1 — Who is connecting? | C13: Identity | D13: Requirement | E13: Authenticate users with at least multifactor authentication. | F13: “Zscaler recommends a minimum of MFA be used to validate users” | G13: 30 | H13: 32 | I13: MFA at the IdP; step-up authentication (Conditional Access action, Authentication Service) | J13: ZPA delegates authentication to the IdP, so MFA is the IdP’s policy. ZPA can demand stronger authentication for sensitive apps only through step-up authentication (authentication levels), which needs an Authentication Service subscription and an OIDC-based external IdP. Zscaler’s AD FS guide (a step marked for AD FS 3.0) selects ‘I do not want to configure multi-factor authentication settings…’ for the relying-party trust, so MFA has to be enforced elsewhere in that design. | K13: Dependency | L13: Configuring Access Policies | M13: https://help.zscaler.com/zpa/configuring-access-policies | N13: Understanding Step-Up Authentication — https://help.zscaler.com/authentication-service/understanding-step-up-authentication Configuration Guide for Microsoft ADFS 2.0 and 3.0 — https://help.zscaler.com/zpa/configuration-guide-microsoft-adfs-20-and-30 | O13: [Configuring Access Policies] “Step-up authentication enforces stronger authentication and only provides access to applications when the authentication matches the additional authentication levels.” [Configuring Access Policies] “Conditional Access: Allows access to sensitive resources for step-up authentication, and is only an option if you are subscribed to Authentication Service.” | P13: [Understanding Step-Up Authentication] “Step-up authentication is supported only with OIDC-based external IdP integrations.” | R13: 2026-10-20
A14: ZT-13 | B14: Element 1 — Who is connecting? | C14: Identity | D14: Requirement | E14: Consume IdP-supplied identity values (groups, department, OU, email, employee ID, geography) chosen by the customer, and use them to differentiate users in policy. | F14: “consume IdP-provided values of identity, certificates, and shared details, including departments, groups, organizational units (OUs), email addresses, etc.” | G14: 30, 31, 33, 42 | H14: 32, 33, 35, 44 | I14: SAML attributes, SCIM attributes and SCIM groups as access-policy criteria | J14: Admins import the SAML attributes they want, or receive users/groups/attributes by SCIM, and use them as rule criteria; ZPA’s assertion can carry more authorisation attributes than Internet & SaaS. SCIM brings a fixed attribute set (no custom attributes). Silent failure: if the IdP’s ‘Attributes for Policy’ setting is off, rules using those criteria are not evaluated. | K14: Native | L14: About SAML Attributes | M14: https://help.zscaler.com/zpa/about-saml-attributes | N14: About SCIM — https://help.zscaler.com/zpa/about-scim About SCIM Groups — https://help.zscaler.com/zpa/about-scim-groups Configuring Access Policies — https://help.zscaler.com/zpa/configuring-access-policies Understanding Policies — https://help.zscaler.com/zpa/understanding-policies | O14: [About SAML Attributes] “You must configure SAML attributes to use them when defining policy rule criteria.” [About SAML Attributes] “In Private Access, various authorization attributes can be provided by the IdP to the Zscaler Client Connector in the SAML assertion, unlike Internet & SaaS, where SAML assertions are restricted to user identity, group, and department attributes.” | P14: [About SCIM] “TheSCIM Attributes page is a read-only table, and Private Access does not support custom attributes. [sic]” [Understanding Policies] “Using NameID as a SAML attribute within access and timeout policy rules is not supported.” | Q14: README lever: tight criteria = IdP group / SCIM attribute / posture; loose = ‘any authenticated user’. | R14: 2026-10-20
A15: ZT-14 | B15: Element 1 — Who is connecting? | C15: Identity | D15: Requirement | E15: Support the common enterprise IdPs: Microsoft Entra ID (Azure AD) and Okta and PingFederate with SAML and SCIM; SailPoint, OneLogin, Google, Microsoft AD FS and CA SSO with SAML. | F15: “Microsoft Azure AD (SAML & SCIM)” | G15: 32 | H15: 34 | I15: IdP configuration guides (any SAML 2.0 IdP) | J15: ZPA supports any SAML 2.0 IdP and publishes ZPA guides for Microsoft Entra ID (still titled Azure AD; SAML and SCIM), Okta, Microsoft AD FS 2.0/3.0, OneLogin and Ping Identity PingOne. PingFederate has a guide only as an Authentication Service external IdP. The ZPA guide index has no entry for Google, SailPoint or CA SSO. | K15: Native | L15: IdP Configuration Guides | M15: https://help.zscaler.com/zpa/authentication/idp-configuration-guides | N15: Configuration Guide for Microsoft Azure AD — https://help.zscaler.com/zpa/configuration-guide-microsoft-azure-ad SCIM Configuration Guide for Microsoft Azure AD — https://help.zscaler.com/zpa/scim-configuration-guide-microsoft-azure-ad Configuration Guide for Okta — https://help.zscaler.com/zpa/configuration-guide-okta Configuration Guide for Microsoft ADFS 2.0 and 3.0 — https://help.zscaler.com/zpa/configuration-guide-microsoft-adfs-20-and-30 Configuration Guide for Onelogin — https://help.zscaler.com/zpa/configuration-guide-onelogin Configuring PingFederate as an External IdP — https://help.zscaler.com/authentication-service/configuring-pingfederate-external-idp Configuring an IdP for Single Sign-On — https://help.zscaler.com/zpa/configuring-idp-single-sign | O15: [Configuring an IdP for Single Sign-On] “The following configuration guides provide instructions on how to configure specific IdPs for SSO, but ZPA can support any IdP.” [Configuration Guide for Microsoft Azure AD] “This guide provides information on how to set up Microsoft Azure Active Directory (AD) as a IdP for Private Access (ZPA).” [Configuration Guide for Microsoft Azure AD] “User-friendly group names are only sent to Azure AD using Azure AD Connect. For example, groups from an on-premise active directory show up in Azure AD when Azure AD Connect syncs the group information.” | P15: [Configuration Guide for Microsoft Azure AD] “A premium Azure AD subscription, or an Azure AD subscription that has used less than 10 gallery Single Sign-On (SSO) applications with the license.” [SCIM Configuration Guide for Microsoft Azure AD] “A premium Azure AD subscription” | Q15: Entra ID is the guide that applies (current-state.md). On-prem AD groups reach ZPA only through Entra sync (Azure AD Connect) — fits the one-way AD → Entra sync recorded here. | R15: 2026-10-20
A16: ZT-15 | B16: Element 1 — Who is connecting? | C16: Identity | D16: Guidance | E16: Derive the first round of user segmentation from HR or organisational structure (e.g. finance vs IT groups). | F16: “Leverage HR departments or the organizational structure to define your first round zero trust differentiation with user group segmentation” | G16: 29, 31 | H16: 31, 33 | I16: Access policy rules by SCIM group or SAML attribute (role-based access control) | J16: Map HR or organisational groups (SCIM groups, or a department attribute) to rules on segment groups — Zscaler’s own example pairs ‘Sales Staff’ with ‘Sales App and Intranet Group’. | K16: Native | L16: About Access Policy | M16: https://help.zscaler.com/zpa/about-access-policy | N16: About SCIM Groups — https://help.zscaler.com/zpa/about-scim-groups Access Policy Configuration Examples — https://help.zscaler.com/zpa/access-policy-configuration-examples | O16: [About Access Policy] “For example, you would specify the users first (i.e., Sales Staff), then specify which application segments or segment groups they can access (i.e., Sales App and Intranet Group).” | Q16: Feeds phase 3 (archetypes) and phase 5 (policy criteria per archetype) in the README. | R16: 2026-10-20
A17: ZT-16 | B17: Element 1 — Who is connecting? | C17: Identity | D17: Requirement | E17: Where initiators at a site cannot be individually authenticated (shared campus network with users, printers and devices), apply policy to the location as an identity. | F17: “by leveraging this location identity, the enterprise can define policies solely for this location” | G17: 32, 33 | H17: 34, 35 | I17: Branch/Cloud Connector groups, Locations and client types in access policy | J17: Traffic a Branch Connector forwards from a site (or a Cloud Connector from a cloud) can be matched by connector group, location or client type — policy for the location, with no user identity. | K17: Other Zscaler product | L17: About Access Policy | M17: https://help.zscaler.com/zpa/about-access-policy | N17: About Branch Connector Groups — https://help.zscaler.com/zpa/about-branch-connector-groups About Cloud Connector Groups — https://help.zscaler.com/zpa/about-cloud-connector-groups Configuring Access Policies — https://help.zscaler.com/zpa/configuring-access-policies Understanding Business Continuity — https://help.zscaler.com/zpa/understanding-business-continuity | O17: [About Access Policy] “Locations: The Branch Connector, Cloud Connector, or other locations and sublocations.” [About Access Policy] “Branch Connector Groups: The group of Branch Connectors to which the policy applies.” | P17: [Understanding Business Continuity] “Browser Access, Source IP Anchoring, Cloud Connector, and Branch Connector client types are not supported.” | Q17: Headless devices (printers, EFTPOS terminals) cannot run Client Connector; location-based policy needs Branch Connector, licensed separately (glossary). | R17: 2026-10-20
A18: ZT-17 | B18: Element 1 — Who is connecting? | C18: Workload & IoT/OT | D18: Requirement | E18: Identify workloads and IoT/OT devices that cannot authenticate to an IdP by location (site, VPC/VNet, VLAN), fingerprinting or tagging — never by IP address alone. | F18: “IoT/OT devices and workloads that cannot perform authentication against an IdP require alternative methods to validate the connection source” “Zscaler best practices recommend not using IP addresses alone as an identity value” | G18: 31, 34, 35, 45, 46 | H18: 33, 36, 37, 47, 48 | I18: Cloud/Branch Connector groups and Workload Groups as policy criteria; Zscaler Microsegmentation for host-level east-west | J18: For workload traffic forwarded into ZPA, policy identifies the source by Cloud/Branch Connector group, location or workload group rather than a user. IoT/OT fingerprinting is not described in the ZPA articles read (see Not ZPA X14); host-agent identity for east-west is Zscaler Microsegmentation. | K18: Other Zscaler product | L18: About Cloud Connector Groups | M18: https://help.zscaler.com/zpa/about-cloud-connector-groups | N18: About Access Policy — https://help.zscaler.com/zpa/about-access-policy What Is Microsegmentation? — https://help.zscaler.com/zpa/what-is-microsegmentation | O18: [About Cloud Connector Groups] “Cloud Connector groups are comprised of individual Cloud Connectors and are used to configure policy rules in the Zscaler Admin Console.” [About Access Policy] “Workload Groups: The Workload Groups from your cloud workloads.” | P18: [What Is Microsegmentation?] “If you want Microsegmentation provisioned for your organization, contact your Zscaler Account team.” | Q18: Out of scope (decision 2026-09-19). EFTPOS terminal → payment switch and agent → collector traffic is invisible to ZPA but must still be known so a user-to-app change does not break it (T-015, T-016). | R18: 2026-10-20
A19: ZT-18 | B19: Element 1 — Who is connecting? | C19: Enforcement | D19: Requirement | E19: Default deny: block until explicitly allowed, and fall back to a conditional block whenever any element's assessment cannot be met; blocks can be invoked at any stage. | F19: “access is completely blocked until explicitly allowed” “If the control assessment of Identity and Context cannot be met, the access must default, as outlined in Figure 11, to a Conditional Block policy.” | G19: 16, 28, 31, 44, 59, 75, 88, 106, 116, 147 | H19: 18, 30, 33, 46, 61, 77, 90, 108, 118, 149 | I19: Implicit Block Access in access policy; Block Access rule action | J19: If no access rule matches — or none exist — access is implicitly blocked; rules are evaluated top-down, first match, against the most specific application segment. Client forwarding policy runs first and defaults to Forward to Private Access, so a Bypass rule removes traffic before access policy (and its default block) is reached. | K19: Native | L19: Understanding Policies | M19: https://help.zscaler.com/zpa/understanding-policies | N19: Configuring Access Policies — https://help.zscaler.com/zpa/configuring-access-policies About Client Forwarding Policy — https://help.zscaler.com/zpa/about-client-forwarding-policy Understanding Private Access Session Status Codes — https://help.zscaler.com/zpa/understanding-private-access-session-status-codes | O19: [Understanding Policies] “For access policy, access to the application is implicitly set to Block Access. This is also the case if you do not define any policy rules at all within the Zscaler Admin Console.” [Configuring Access Policies] “By default, Private Access (ZPA) blocks access to applications and segment groups for users until you configure policy rules that explicitly allow access.” | P19: [Understanding Policies] “For client forwarding policy, access to the application is implicitly set to Forward to Private Access.” | Q19: README: client forwarding policy is evaluated before access policy, so a BYPASS is not a block and leaves no user activity record. ~10 BYPASS rules exist, none with an expiry (T-054). A default deny is logged with the status code for ‘no policy configured’ (Understanding Private Access Session Status Codes). | R19: 2026-10-20
A20: ZT-19 | B20: Element 2 — What are the attributes? | C20: Context & posture | D20: Requirement | E20: Distinguish trusted from untrusted and defined from undefined locations/networks (e.g. office vs home or guest network) and use that in policy. | F20: “A trusted location should be governed by enterprise-defined conditions that reduce its risk profile.” | G20: 39, 40, 42 | H20: 41, 42, 44 | I20: Client Connector Trusted Networks (access policy, client forwarding policy, forwarding profiles) | J20: Admins define trusted networks by conditions (DNS server, DNS search domains, hostname/IP resolution, network range, default gateway, DHCP server, egress IP); Client Connector detects them and the result can be used in access policy, client forwarding policy and forwarding profiles. | K20: Native | L20: Configuring Trusted Networks for Zscaler Client Connector | M20: https://help.zscaler.com/zscaler-client-connector/configuring-trusted-networks-zscaler-client-connector | N20: About Access Policy — https://help.zscaler.com/zpa/about-access-policy Configuring Forwarding Profiles for Zscaler Client Connector — https://help.zscaler.com/zscaler-client-connector/configuring-forwarding-profiles-zscaler-client-connector Configuring Access Policies — https://help.zscaler.com/zpa/configuring-access-policies | O20: [Configuring Trusted Networks for Zscaler Client Connector] “To have Zscaler Client Connector identify one of your organization’s trusted networks, you must define conditions for that network as criteria that Zscaler Client Connector uses for verification.” [About Access Policy] “Client Connector Trusted Networks: The type of network the user is connected to that Zscaler Client Connector can trust.” | P20: [Configuring Trusted Networks for Zscaler Client Connector] “If a resolution fails, the app could incorrectly determine that the network is an untrusted one, in which case it applies the wrong forwarding profile action.” [Configuring Access Policies] “The posture profiles or trusted networks criteria only work with Client Connector.” | Q20: SYDNEY LAN users are brokered through the private service edge (README). | R20: 2026-10-20
A21: ZT-20 | B21: Element 2 — What are the attributes? | C21: Context & posture | D21: Requirement | E21: Control access by geography (country), e.g. restrict access from sanctioned countries. | F21: “user access from specific sanctioned countries should be controlled” | G21: 39, 40 | H21: 41, 42 | I21: Country Codes access-policy criterion | J21: Rules can allow or block by the country the user’s public IP is located in. For a user reaching a Private Service Edge from an RFC 1918 address, the PSE’s location is used instead. | K21: Native | L21: About Access Policy | M21: https://help.zscaler.com/zpa/about-access-policy | N21: Configuring Access Policies — https://help.zscaler.com/zpa/configuring-access-policies About Private Service Edges — https://help.zscaler.com/zpa/about-private-service-edges | O21: [About Access Policy] “Country Codes: The country that a user's IP address is located in.” [About Private Service Edges] “If a user connects to a Private Service Edge with an RFC 1918 IP address, then the location of the Private Service Edge is used to evaluate policies with country criteria.” | P21: [Configuring Access Policies] “The Country Codes criteria type is not supported in Browser Access or Privileged Remote Access Applications.” | Q21: SYDNEY LAN users brokered by the PSE from RFC 1918 addresses are evaluated at the PSE’s location, not their own (About Private Service Edges). | R21: 2026-10-20
A22: ZT-21 | B22: Element 2 — What are the attributes? | C22: Context & posture | D22: Requirement | E22: Detect and stop the 'impossible traveller' (access from distant locations in quick succession). | F22: “Geographic controls can also be used to stop the “impossible traveler”” | G22: 40, 72 | H22: 42, 74 | I22: None native. Nearest: Risk Scores criterion (user risk from Internet & SaaS); Adaptive Access profiles | J22: No impossible-travel or geovelocity signal appears in the ZPA or Adaptive Access Engine articles read. ZPA can consume a user risk score computed by Internet & SaaS, and Adaptive Access profiles, but neither article says impossible travel feeds them. The control has to come from a risk engine outside ZPA. | K22: Gap | L22: About User Risk Scores | M22: https://help.zscaler.com/zpa/about-user-risk-scores | N22: Understanding Adaptive Access Engine — https://help.zscaler.com/unified/understanding-adaptive-access-engine Understanding User Risk Score — https://help.zscaler.com/zia/understanding-user-risk-score | O22: [About User Risk Scores] “User risk scores are generated based on a user’s DLP violations, risky behavior, unsanctioned cloud application usage, and other suspicious factors.” [About User Risk Scores] “You can add user risk scores as a criteria type to access policy rules.” | P22: [About User Risk Scores] “User risk scores are not supported in User Portals or Privileged Remote Access Portals.” | R22: 2026-10-20
A23: ZT-22 | B23: Element 2 — What are the attributes? | C23: Context & posture | D23: Requirement | E23: Use time of request (within or outside defined time bands, e.g. business hours) as a policy condition. | F23: “The time that a user requests a connection to an application is another attribute zero trust architecture can base policy on.” | G23: 39, 41 | H23: 41, 43 | I23: None — no time-of-day criterion in access policy | J23: Access-policy criteria (Who / What / Where) contain no time-of-day or schedule condition. The nearest time-bound controls are timeout policy (re-authentication and idle timeouts) and PRA privileged approvals with a start and end time for named users. | K23: Gap | L23: Configuring Access Policies | M23: https://help.zscaler.com/zpa/configuring-access-policies | N23: Configuring Timeout Policies — https://help.zscaler.com/zpa/configuring-timeout-policies About Privileged Approvals — https://help.zscaler.com/zpa/about-privileged-approvals | O23: [Configuring Access Policies] Criteria as listed — Who: SAML and SCIM Attributes; External IAM IdPs. What: Applications; Branch Connector Groups; Chrome Enterprise Browser; Client Connector Posture Profiles; Client Connector Trusted Networks; Client Types; Cloud Connector Groups; Federated Applications; Machine Groups; Platforms; Risk Scores. Where: Country Codes; Extranet Location; Locations. [About Privileged Approvals] “Create privileged approvals with a set amount of time that one or more designated application segments can be accessed.” | P23: [About Privileged Approvals] “Privileged approvals allow third-party users and contractors to be able to log in to a Privileged Remote Access (PRA) Portal.” | R23: 2026-10-20
A24: ZT-23 | B24: Element 2 — What are the attributes? | C24: Context & posture | D24: Requirement | E24: Differentiate managed (corporate) from unmanaged (BYOD, contractor) devices and restrict untrusted devices appropriately. | F24: “we must further differentiate between managed and unmanaged devices” “The personal device must be identified as untrusted and access restricted appropriately.” | G24: 33, 41, 42, 43, 44 | H24: 35, 43, 44, 45, 46 | I24: Client Types + Client Connector posture profiles | J24: There is no single ‘managed device’ criterion. Pattern implied by the criteria: Client Connector client type plus a verified posture profile (e.g. Domain Joined, AzureAD Domain Joined, Client Certificate) for managed devices; the Web Browser client type for unmanaged ones, where posture and trusted-network criteria cannot be used. | K24: Native | L24: Configuring Access Policies | M24: https://help.zscaler.com/zpa/configuring-access-policies | N24: About Access Policy — https://help.zscaler.com/zpa/about-access-policy Configuring Device Posture Profiles — https://help.zscaler.com/zscaler-client-connector/configuring-device-posture-profiles | O24: [Configuring Access Policies] “Rules using the Web Browser or Internet & SaaS Service Edge client types additionally can't use posture profiles or trusted networks criteria.” [About Access Policy] “Client Connector Posture Profiles: Zscaler Client Connector device posture profiles are the set of criteria that a user's device must meet to access applications with Private Access.” | Q24: With Browser Access out of scope, an unmanaged device is refused rather than restricted (decision 2026-09-27). | R24: 2026-10-20
A25: ZT-24 | B25: Element 2 — What are the attributes? | C25: Context & posture | D25: Requirement | E25: Assess device posture — operating system, antivirus, EDR presence, domain membership, disk encryption — evaluated by the endpoint agent without calling out to external sources. | F25: “without having to call out to external sources for validation” | G25: 41, 42, 72 | H25: 43, 44, 74 | I25: Client Connector device posture profiles | J25: Client Connector evaluates posture on the device — OS Version, Detect Antivirus, Detect Microsoft Defender / CrowdStrike / SentinelOne / Carbon Black, Firewall, Full Disk Encryption, Domain Joined and more — every 2–15 minutes (EDR and process checks immediately on change). Access policy sees only the outcome. | K25: Native | L25: Configuring Device Posture Profiles | M25: https://help.zscaler.com/zscaler-client-connector/configuring-device-posture-profiles | N25: About Device Posture Profiles — https://help.zscaler.com/zscaler-client-connector/about-device-posture-profiles About Access Policy — https://help.zscaler.com/zpa/about-access-policy | O25: [Configuring Device Posture Profiles] “For each posture type, select how often Zscaler Client Connector evaluates device posture by selecting a value, in one-minute intervals, from the drop-down menu. The maximum default value is 15 minutes. The minimum value is 2 minutes.” | P25: [Configuring Device Posture Profiles] “Not all device posture types work for all platforms.” [Configuring Device Posture Profiles] “Zscaler Client Connector doesn't check for the presence of third-party firewalls. Third-party firewalls don't fulfill the posture check requirement.” | Q25: backlog T-053 treats a posture failure as a distinct onboarding-failure cause. | R25: 2026-10-20
A26: ZT-25 | B26: Element 2 — What are the attributes? | C26: Context & posture | D26: Requirement | E26: Validate a client certificate as proof of a managed device. | F26: “client certificate validation” | G26: 42, 72 | H26: 44, 74 | I26: Client Certificate, Certificate Trust and Server Validated Client Certificate posture types | J26: Posture profiles can require a client certificate on the device; the Server Validated Client Certificate type applies to Private Access only. | K26: Native | L26: Configuring Device Posture Profiles | M26: https://help.zscaler.com/zscaler-client-connector/configuring-device-posture-profiles | O26: [Configuring Device Posture Profiles] Posture types listed include Client Certificate, Certificate Trust and Server Validated Client Certificate. [Configuring Device Posture Profiles] “This posture is applicable to Private Access (ZPA) only.” | P26: [Configuring Device Posture Profiles] “As of Zscaler Client Connector version 5.0 for Android, Zscaler is ending support for the Client Certificate posture type for all Android devices.” [Configuring Device Posture Profiles] “Client certificates that require user interaction (e.g., smart cards with a PIN) are not supported.” | R26: 2026-10-20
A27: ZT-26 | B27: Element 2 — What are the attributes? | C27: Context & posture | D27: Requirement | E27: Integrate third-party EDR/AV (and other security tools) via API to enrich device and risk context. | F27: “sometimes via APIs from other third-party systems like endpoint detection and response (EDR) vendors” “Those garnered from EDR, SIEM, or SOAR services may add context for improved determinations.” | G27: 33, 42, 75, 81 | H27: 35, 44, 77, 83 | I27: EDR posture checks (CrowdStrike ZTA score; Defender, SentinelOne, Carbon Black detection; Jamf risk) and Adaptive Access Engine integrations | J27: Two mechanisms. On the device, posture checks test a CrowdStrike ZTA score threshold, presence of Defender, SentinelOne or Carbon Black, or a Jamf risk level. In the cloud, the Adaptive Access Engine ingests CrowdStrike and Microsoft Defender signals into Adaptive Access profiles usable in ZPA policy. | K27: Dependency | L27: Configuring Device Posture Profiles | M27: https://help.zscaler.com/zscaler-client-connector/configuring-device-posture-profiles | N27: Integrating CrowdStrike with Adaptive Access Engine — https://help.zscaler.com/unified/integrating-crowdstrike-adaptive-access-engine Integrating Microsoft Defender with Adaptive Access Engine — https://help.zscaler.com/unified/integrating-microsoft-defender-adaptive-access-engine Understanding Adaptive Access Engine — https://help.zscaler.com/unified/understanding-adaptive-access-engine | O27: [Configuring Device Posture Profiles] “Zscaler Client Connector compares this number against an overall score (a combined score based on the device OS settings and sensor settings) assigned by CrowdStrike's user agent. If that overall score is greater than or equal to the score you've entered, the posture check passes.” [Integrating Microsoft Defender with Adaptive Access Engine] “Risk Score: Values are None, Informational, Low, Medium, and High.” | P27: [Configuring Device Posture Profiles] “Users must enable the CrowdStrike ZTA feature in CrowdStrike. Contact CrowdStrike Support to enable this feature.” [Integrating CrowdStrike with Adaptive Access Engine] “This integration is in limited availability. Contact Zscaler Support for assistance.” [Integrating Microsoft Defender with Adaptive Access Engine] “A Microsoft Azure account with subscription for Event Hub and Logic App.” [Understanding Adaptive Access Engine] “Authentication Service for end users is enabled or end user migration to Authentication Service is completed.” | R27: 2026-10-20
A28: ZT-27 | B28: Element 2 — What are the attributes? | C28: Context & posture | D28: Requirement | E28: Detect jailbroken (or rooted) handhelds. | F28: “jailbroken or not (for handhelds)” | G28: 42 | H28: 44 | I28: Unauthorized Modification posture type (Android, iOS) | J28: Client Connector checks mobile devices for jailbreaking or rooting. | K28: Native | L28: Configuring Device Posture Profiles | M28: https://help.zscaler.com/zscaler-client-connector/configuring-device-posture-profiles | O28: [Configuring Device Posture Profiles] “Zscaler Client Connector checks for unauthorized modifications on the device, such as jailbreaking or rooting.” | R28: 2026-10-20
A29: ZT-28 | B29: Element 2 — What are the attributes? | C29: Context & posture | D29: Requirement | E29: Combine multiple ('stacked') posture tests into one outcome consumed by policy. | F29: “Having these variations of stacked device posture tests allows an enterprise to consume the outcomes of these posture assessments as an additional layer of user context” | G29: 42 | H29: 44 | I29: Multiple criteria per rule with Boolean AND/OR | J29: A rule can combine several posture profiles with other context; a request must match all of a rule’s conditions, so stacked tests resolve to one allow/block outcome. | K29: Native | L29: About Access Policy | M29: https://help.zscaler.com/zpa/about-access-policy | N29: Configuring Access Policies — https://help.zscaler.com/zpa/configuring-access-policies | O29: [About Access Policy] “A user's application request must match all the conditions within a policy rule.” [About Access Policy] “Access Policy rules use AND and OR operators only.” | R29: 2026-10-20
A30: ZT-29 | B30: Element 3 — Where is the connection going? | C30: Application definition | D30: Requirement | E30: Define internal applications explicitly — by name (FQDN, internal domains) or private IP — and cover web and non-web (SSH, RDP, other TCP/UDP) protocols. | F30: “These apps exist in internal address spaces, e.g., server1.local, or on a private IP (RFC-1918) space.” “Customers can also manually create and modify their own app segments based on their application classification requirements.” | G30: 48, 54, 57, 63, 65 | H30: 50, 56, 59, 65, 67 | I30: Application segments (defined applications) | J30: An application segment defines apps by FQDN, IP address, local domain or wildcard domain (IP subnets for discovery), with TCP and UDP port ranges, so web and non-web protocols are covered. | K30: Native | L30: Configuring Defined Application Segments | M30: https://help.zscaler.com/zpa/configuring-defined-application-segments | N30: About Applications — https://help.zscaler.com/zpa/about-applications Application Discovery Deployment and Operations Guide — https://help.zscaler.com/zscaler-deployments-operations/application-discovery-deployment-and-operations-guide | O30: [Configuring Defined Application Segments] “Enter a fully qualified domain name (FQDN), IP address, local domain, or a wildcard domain (e.g., *.safemarch.com) associated with the application.” [Configuring Defined Application Segments] “TCP Port Ranges: Enter the TCP port ranges that can be used to access the application.” [Configuring Defined Application Segments] “UDP Port Ranges: Enter the UDP port ranges that can be used to access the application.” | P30: [Configuring Defined Application Segments] “You can't define an application with hyphenated IP address ranges (e.g., 192.168.0.1–10).” | Q30: README lever: tight = specific FQDN + specific ports; loose = wildcard FQDN, broad CIDR, 1-65535. Exact match pulls a destination out of the wildcard the moment a narrower segment exists, so each replacement segment needs its full port set before it is built (destination-port-profile.spl). | R30: 2026-10-20
A31: ZT-30 | B31: Element 3 — Where is the connection going? | C31: Segmentation | D31: Requirement | E31: Write access policy rules that first define the users, then the individual application segments or segment groups they may reach, using criteria such as user profile, device posture, connected network and IdP attributes. | F31: “These rules define the users and then define which applications or segment groups they can access.” “The criteria used to create these controls include user profile, device posture, connected network, IdP attributes, and others.” | G31: 68 | H31: 70 | I31: Access policy | J31: Rules define the users, then the application segments or segment groups they may reach, with further criteria such as posture profiles, trusted networks, client types, connector groups, machine groups and SAML/SCIM attributes. The book’s wording on p.68 matches Zscaler’s help article almost word for word. | K31: Native | L31: About Access Policy | M31: https://help.zscaler.com/zpa/about-access-policy | N31: Configuring Access Policies — https://help.zscaler.com/zpa/configuring-access-policies | O31: [About Access Policy] “Use additional criteria to restrict access based on device posture profile conditions, trusted networks, client types, Cloud Connector groups, machine groups, and SAML or SCIM attributes.” | P31: [Configuring Access Policies] “The maximum limit of selected App Connector groups is 48. If All App Connector groups for the application is selected and there are more than 48 configured for your organization, then only 48 App Connector groups are used.” | Q31: Phase 5 policy design: access + client forwarding + timeout policy, criteria per archetype (README). | R31: 2026-10-20
A32: ZT-31 | B32: Element 3 — Where is the connection going? | C32: Segmentation | D32: Requirement | E32: Categorise applications (e.g. mission critical, finance, engineering) and assign each category to policy. | F32: “After an app is categorized, it must be assigned to a policy to ensure traffic destined for the app is correctly controlled.” | G32: 48, 66, 147 | H32: 50, 68, 149 | I32: Segment groups; tag management (namespaces and tags) as criteria | J32: Each application segment belongs to exactly one segment group, which access policy can target; tags (key/value metadata such as ‘Critical’) add classification across groups and can also be used as access-policy criteria. | K32: Native | L32: About Segment Groups | M32: https://help.zscaler.com/zpa/about-segment-groups | N32: About Tag Management for Application Segments — https://help.zscaler.com/zpa/about-tag-management-application-segments Configuring Tags and Namespaces for Application Segments — https://help.zscaler.com/zpa/configuring-tags-and-namespaces-application-segments Configuring Access Policies — https://help.zscaler.com/zpa/configuring-access-policies | O32: [About Segment Groups] “You must place each application segment you configure into a segment group. This allows you to configure user access policies based on segment groups.” [About Tag Management for Application Segments] “Tag Management involves creating namespaces and tags to classify and group resources in Private Access (ZPA).” | P32: [About Segment Groups] “However, you cannot assign an application segment to multiple segment groups.” [Configuring Tags and Namespaces for Application Segments] “Predefined namespaces and tags cannot be edited or deleted.” | Q32: README: segment groups bundle app segments for policy; server groups bind them to connectors. | R32: 2026-10-20
A33: ZT-32 | B33: Element 3 — Where is the connection going? | C33: Segmentation | D33: Requirement | E33: Define critical applications from a classification standard (SOC 2, PCI or similar) and give them the most restrictive rules; protect known-critical assets with specific policy first. | F33: “Critical apps must be differentiated in policy and access control from less critical apps, where access is more open.” “beginning with a specific policy to protect “known-critical” assets if possible” | G33: 52, 56, 59 | H33: 54, 58, 61 | I33: Granular segments + restrictive access policy; tags for criticality | J33: ZPA supplies the constructs — granular segments without wildcards, tags or segment groups for criticality, tight criteria (groups, posture, step-up) — but the classification itself (SOC 2, PCI) is the customer’s. Zscaler’s discovery guide calls for granular segments and least-privilege policy once apps are found. | K33: Partial | L33: Application Discovery Deployment and Operations Guide | M33: https://help.zscaler.com/zscaler-deployments-operations/application-discovery-deployment-and-operations-guide | N33: Configuring Tags and Namespaces for Application Segments — https://help.zscaler.com/zpa/configuring-tags-and-namespaces-application-segments Configuring Access Policies — https://help.zscaler.com/zpa/configuring-access-policies | O33: [Application Discovery Deployment and Operations Guide] “After applications are discovered, define granular application segments and access policies to restrict access on a least-privilege access principle.” [Configuring Tags and Namespaces for Application Segments] “Values: Enter values for the tags (e.g., High, Critical, San Jose, HQ, etc.).” | Q33: Telnet apps carry no identity or encryption, so segmentation is the compensating control — tighten them first (current-state.md). PCI DSS scope for EFTPOS is open (T-010). | R33: 2026-10-20
A34: ZT-33 | B34: Element 3 — Where is the connection going? | C34: Discovery | D34: Guidance | E34: Start with a broad (*.*) application policy that mimics VPN reach while removing the exposed VPN, then narrow: define each application group with all its names and IPs, map the users who need it, and conditionally block everyone else. | F34: “applying a *.* application policy” “with a *.* access policy to mimic existing VPN access” | G34: 68, 146, 147 | H34: 70, 148, 149 | I34: Wildcard-domain and IP-subnet application segments for application discovery | J34: Broad segments (wildcard domains such as *.example.com, IP subnets, wide port ranges) with a broad access rule replicate VPN reach while ZPA discovers what is used. A bare ‘*’ application needs Zscaler’s approval, must be alone in its segment and is excluded from discovery — so the book’s ‘*.*’ becomes wildcard domains plus subnets in practice. | K34: Native | L34: Configuring Defined Application Segments | M34: https://help.zscaler.com/zpa/configuring-defined-application-segments | N34: Understanding Application Discovery — https://help.zscaler.com/zpa/understanding-application-discovery Application Discovery Deployment and Operations Guide — https://help.zscaler.com/zscaler-deployments-operations/application-discovery-deployment-and-operations-guide Using Application Segment Multimatch — https://help.zscaler.com/zpa/using-app-segment-multimatch | O34: [Configuring Defined Application Segments] “You can also define the application with a wildcard only (i.e., *), but this should be the only application in the application segment. You can't define an application this way unless approved by Zscaler. Contact Zscaler Support for more information.” [Understanding Application Discovery] “Application discovery works efficiently when the TCP and UDP port range specified for the domain is wide, and when the application policy allows access to a broad set of users.” | P34: [Application Discovery Deployment and Operations Guide] “Applications defined with only a wildcard, i.e., an asterisk (*), are not available for application discovery.” [Using Application Segment Multimatch] “By default, after a specific FQDN is configured in an application segment, the destination is removed from the wildcard application segment.” | Q34: Deployed: as-CatchAll = *.example.com, data from 1 Jun 2026 (README). A wildcard domain, not *.*: traffic with no name (IP literals, hosts files, short names) never enters ZPA and is absent from discovery. | R34: 2026-10-20
A35: ZT-34 | B35: Element 3 — Where is the connection going? | C35: Discovery | D35: Requirement | E35: Discover and inventory internal applications actually used (who accessed which application, not just IPs), flagging newly identified apps so they can be assigned a segment and policy. | F35: “Internal apps must be flagged as newly identified, allowing the enterprise to determine which segment, app definition, policy, etc., best describe them.” “Accumulate granular application inventory, not limited to IP address, of accessed applications.” | G35: 52, 55, 56, 131, 146 | H35: 54, 57, 58, 133, 148 | I35: Application discovery (Applications Discovered in Past 14 Days); LSS User Activity | J35: ZPA discovers an application only when a user requests it through a broad segment; discovered apps can be defined as segments from the Applications dashboard. Diagnostics hold discovery data for 14 days, so a lasting inventory needs LSS User Activity in the SIEM. | K35: Native | L35: Understanding Application Discovery | M35: https://help.zscaler.com/zpa/understanding-application-discovery | N35: Defining a Dynamically Discovered Application — https://help.zscaler.com/zpa/defining-dynamically-discovered-application Application Discovery Deployment and Operations Guide — https://help.zscaler.com/zscaler-deployments-operations/application-discovery-deployment-and-operations-guide Understanding User Activity Log Fields — https://help.zscaler.com/zpa/understanding-user-activity-log-fields | O35: [Understanding Application Discovery] “Private Access only discovers an application when a user requests access to it. After an application is discovered, you can define granular policies for your discovered applications to control access.” [Understanding Application Discovery] “If you want to create a policy for a discovered application or configure specific settings for it (e.g., choosing Continuous health reporting), you can define the discovered application from the Applications Discovered in Past 14 Days widget on the Applications dashboard.” | P35: [Application Discovery Deployment and Operations Guide] “After 14 days, discovered application data is no longer listed in the User Activity Diagnostics.” [Understanding Application Discovery] “You can only choose On Access health reporting for discovered applications.” | Q35: Discovery evidence is LSS user activity for as-CatchAll; host count under reconciliation (~5,000 over 7 days vs 1,888 from 1 Jun; T-003). It is the unsegmented remainder, not the estate (README). | R35: 2026-10-20
A36: ZT-35 | B36: Element 3 — Where is the connection going? | C36: Discovery | D36: Requirement | E36: Treat unknown (not yet categorised) applications as untrusted and subject them to the strictest control and enforcement until categorised. | F36: “These apps should be considered untrustworthy and risky until proven otherwise.” | G36: 55 | H36: 57 | I36: Access policy and AppProtection on the discovery segment (design choice) | J36: ZPA has no automatic risk classification for unknown internal apps. Scrutiny is a design choice on the discovery segment: who may use it (groups, posture), for how long (Zscaler says to set a deadline for turning discovery off), and optional AppProtection on web traffic. Note the tension: Zscaler says discovery works best with wide ports and broad user access. | K36: Partial | L36: Application Discovery Deployment and Operations Guide | M36: https://help.zscaler.com/zscaler-deployments-operations/application-discovery-deployment-and-operations-guide | N36: Understanding Application Discovery — https://help.zscaler.com/zpa/understanding-application-discovery About AppProtection Policy — https://help.zscaler.com/zpa/about-appprotection-policy | O36: [Application Discovery Deployment and Operations Guide] “Define a deadline after which application discovery is turned off to enforce the least-privilege access principle for all discovered applications.” | Q36: Compare with the as-CatchAll access rule: the book’s own discovery example (p.53) admits 20,000 users on EDR posture alone. | R36: 2026-10-20
A37: ZT-36 | B37: Element 3 — Where is the connection going? | C37: Discovery | D37: Requirement | E37: Use machine learning over observed user-to-application flows to recommend segments and access policies (shrink who can reach each application). | F37: “Machine learning-based techniques allow Zscaler to recommend access policies based on the actual traffic flows.” | G37: 53, 68, 140, 147 | H37: 55, 70, 142, 149 | I37: AI-Powered Recommendations for Application Segments | J37: ZPA analyses user logs and recommends new application segments, the users and groups who need them, and a matching policy; accepting a recommendation creates the segment and the policy rule. | K37: Native | L37: About AI-Powered Recommendations for Application Segments | M37: https://help.zscaler.com/zpa/about-ai-powered-recommendations-application-segments | N37: About Policy Recommendations for Resource Groups — https://help.zscaler.com/zpa/about-policy-recommendations-resource-groups | O37: [About AI-Powered Recommendations for Application Segments] “Private Access (ZPA) analyzes user logs and suggests AI-powered recommendations for application segments.” [About AI-Powered Recommendations for Application Segments] “Discover and create new application segments based on application similarity or user behavior.” | P37: [About AI-Powered Recommendations for Application Segments] “Have a minimum of 100 discovered applications.” [About AI-Powered Recommendations for Application Segments] “Have at least 20 enrolled users.” [About AI-Powered Recommendations for Application Segments] “The Next Availability date and the ability to generate AI-powered recommendations are determined by your subscription.” [About AI-Powered Recommendations for Application Segments] “Before adding recommendations to application segments, ensure that Multimatch is enabled on the wildcard application segment.” [About AI-Powered Recommendations for Application Segments] “If SCIM Sync or SCIM Attributes for Policy is not enabled, the user recommendations appear as N/A.” | Q37: Needs Multimatch on the wildcard segment; whether Multimatch is enabled here is captured under T-041. Any flow-based recommendation also inherits its observation window and cannot see month-end or FY-end traffic absent from it (zpa/docs/enterprise-application-segmentation-methodologies.md). | R37: 2026-10-20
A38: ZT-37 | B38: Element 3 — Where is the connection going? | C38: Application definition | D38: Requirement | E38: Group non-web services by function under one application definition, e.g. 'all file servers' = every name and IP of the file servers on TCP 445 (SMB). | F38: “like “All file servers” as a group that contains all IP addresses, FQDNs, and domain names for all servers that host file servers running on port 445 (SMB)” | G38: 48, 58 | H38: 50, 60 | I38: Application segment with many domains/IPs on one port | J38: One segment can list many domains or IP addresses with a single TCP port (e.g. 445 entered as From and To). A host also defined in a more specific segment is carved out of this one under the default exact match. | K38: Native | L38: Configuring Defined Application Segments | M38: https://help.zscaler.com/zpa/configuring-defined-application-segments | N38: Using Application Segment Multimatch — https://help.zscaler.com/zpa/using-app-segment-multimatch | O38: [Configuring Defined Application Segments] “Click Add More to add more domains or IP addresses for each application you want to define.” [Configuring Defined Application Segments] “If you only want to specify one port, you can enter the same number (e.g., 80) for From... and To....” | P38: [Using Application Segment Multimatch] “Exact match is the default behavior.” | Q38: destination-port-profile.spl gives the port set each replacement segment must carry. | R38: 2026-10-20
A39: ZT-38 | B39: Element 3 — Where is the connection going? | C39: Clientless & privileged access | D39: Requirement | E39: Provide privileged remote access for workforce and third parties to servers and OT/ICS/SCADA: fully isolated, clientless RDP/SSH from any HTML5 browser. | F39: “This allows for fully isolated, clientless RDP/SSH as well as secure file/data transfers.” “Fully isolated RDP/SSH access over any HTML5 capable browser” | G39: 46, 57, 58, 129 | H39: 48, 59, 60, 131 | I39: Privileged Remote Access (PRA) | J39: PRA is a clientless remote desktop gateway: users reach servers, jump hosts or desktops over RDP, SSH, VNC and RealVNC from a browser, through privileged portals and consoles. Audience: third parties, IT admins, remote employees. Telnet is not among the listed protocols, and the PRA articles do not mention OT. | K39: Native | L39: Understanding Privileged Remote Access | M39: https://help.zscaler.com/zpa/understanding-privileged-remote-access | N39: About Privileged Approvals — https://help.zscaler.com/zpa/about-privileged-approvals About Managed Privileged Credentials — https://help.zscaler.com/zpa/about-privileged-managed-credentials | O39: [Understanding Privileged Remote Access] “PRA allows you to provide third parties (vendors, contractors, suppliers), IT administrators, and remote employees controlled access to your privileged servers and applications.” [Understanding Privileged Remote Access] “Privileged portals are designated with a URL and a Browser Access certificate that the Private Access (ZPA) infrastructure uses when an end user accesses a privileged portal.” | P39: [Understanding Privileged Remote Access] “You might see both PRA policy options, only one, or neither in your Zscaler Admin Console depending on your enablement of these policy options.” [Understanding Privileged Remote Access] “The emergency access users are managed in an Okta IdP but can be viewed on the Emergency Access Users page within the Zscaler Admin Console.” | Q39: Not addressed by the Browser Access decision. Admin RDP/SSH to back-end servers is user-to-app and in scope (decision 2026-09-19). PRA lists no telnet, so the estate’s telnet apps need another path. Open: privileged portals use a Browser Access certificate — confirm the Browser Access decision does not close PRA too. | R39: 2026-10-20
A40: ZT-39 | B40: Element 3 — Where is the connection going? | C40: Clientless & privileged access | D40: Requirement | E40: Record privileged remote sessions. | F40: “Session Recording” | G40: 58, 129 | H40: 60, 131 | I40: PRA session recording and live monitoring (consoles policy) | J40: With a consoles policy, PRA records the screen output of privileged console sessions; admins can view live and recorded sessions and join (monitor) a live one. | K40: Native | L40: Accessing Privileged Sessions | M40: https://help.zscaler.com/zpa/accessing-privileged-sessions | N40: Understanding Privileged Remote Access — https://help.zscaler.com/zpa/understanding-privileged-remote-access | O40: [Accessing Privileged Sessions] “After you have created a consoles policy, you can record the screen output of a privileged console session.” [Accessing Privileged Sessions] “Admins can view both live privileged sessions and recorded privileged sessions for malicious activity and error prevention.” | P40: [Accessing Privileged Sessions] “For tenants created on or before November 3, 2022, an administrator must explicitly enable it, otherwise termination requests might not disconnect the active session.” | R40: 2026-10-20
A41: ZT-40 | B41: Element 3 — Where is the connection going? | C41: Clientless & privileged access | D41: Requirement | E41: Provide secure file/data transfer for privileged (OT) remote access. | F41: “secure file/data transfers” | G41: 57 | H41: 59 | I41: PRA File Transfer System | J41: Two features: File Transfer inside a privileged console (when enabled), and the PRA File Transfer System on the PRA portal, where a portals policy governs deleting files, access to uninspected files and uploading files inspected by DI scan or Sandbox. | K41: Native | L41: About the Privileged Remote Access (PRA) File Transfer System | M41: https://help.zscaler.com/zpa/about-privileged-remote-access-pra-file-transfer-system | N41: Understanding Privileged Remote Access — https://help.zscaler.com/zpa/understanding-privileged-remote-access | O41: [About the Privileged Remote Access (PRA) File Transfer System] “If a user has the PRA File Transfer System feature enabled, they can click on the PRA File Transfer System icon on the PRA Portal page.” [Understanding Privileged Remote Access] “File Transfer allows an end user to upload and download files within a privileged console if these features are enabled.” | P41: [About the Privileged Remote Access (PRA) File Transfer System] “You can upload up to 10 files for each privileged portal.” [About the Privileged Remote Access (PRA) File Transfer System] “You can upload a file with a maximum limit of up to 1 GB.” [About the Privileged Remote Access (PRA) File Transfer System] “The admin must also configure a portals policy to enable the following actions: deleting a file, accessing uninspected files, uploading an inspected file (via DI scan or Sandbox).” | R41: 2026-10-20
A42: ZT-41 | B42: Element 3 — Where is the connection going? | C42: Deception | D42: Requirement | E42: Let policy send compromised users or attackers to decoy applications that mimic production (honeypots), raising high-fidelity alerts. | F42: “Policy definitions should include the ability to define alternate destinations for app access.” “This decoy cloud will mimic the behavior of an actual internal application while preventing lateral movement and the loss of sensitive data.” | G42: 48, 59, 67, 114, 120 | H42: 50, 61, 69, 116, 122 | I42: Zscaler Deception integrated with Private Access (decoy apps, containment) | J42: Deception uses ZPA to publish decoy applications in a dedicated Deception cloud; when an adversary touches a decoy, Deception applies access policy so the user can reach only decoys. Access rules created by Deception cannot be copied, edited or deleted in ZPA. | K42: Other Zscaler product | L42: Understanding the Zscaler Deception Architecture | M42: https://help.zscaler.com/deception/understanding-zscaler-deception-architecture | N42: Containment Configuration Guide for Private Access — https://help.zscaler.com/deception/containment-configuration-guide-private-access About Access Policy — https://help.zscaler.com/zpa/about-access-policy | O42: [Understanding the Zscaler Deception Architecture] “Deception integrated with Zscaler Private Access (ZPA) leverages the Zero Trust Network Access (ZTNA) solution that allows you to create decoy applications that look like they exist within your organization's environment, but leverage ZPA's technology to redirect adversaries to the Deception cloud.” [Containment Configuration Guide for Private Access] “If a user is contained with Private Access, real apps become inaccessible and only app decoys remain accessible.” | P42: [About Access Policy] “Updating the rule order of an access policy configured using Zscaler Deception is not supported.” [Containment Configuration Guide for Private Access] “Signed in to the Zscaler Admin Console and configured an IdP for single sign-on (SSO) in Private Access.” | R42: 2026-10-20
A43: ZT-42 | B43: Element 3 — Where is the connection going? | C43: Connectivity | D43: Requirement | E43: Split internal from external traffic at the client and steer private traffic automatically over an outbound-only TLS/DTLS tunnel, with no manual tunnel configuration; manage bypass and forwarding centrally. | F43: “steer it over the correct tunnel to the correct security edge service” “The Client Connector is designed for this automated path steering and does not require any manual configuration of tunnels.” | G43: 60, 61, 133, 136 | H43: 62, 63, 135, 138 | I43: Client Connector forwarding profile + ZPA client forwarding policy | J43: Client Connector identifies internal applications and tunnels them to Private Access while other traffic goes to Internet & SaaS. The forwarding profile sets ZPA treatment per network type; client forwarding policy — evaluated before access policy, first match — chooses Forward to ZPA, Bypass ZPA or Only Forward Allowed Applications. Both are managed centrally. The docs describe the tunnel as TLS-encrypted. | K43: Native | L43: About Client Forwarding Policy | M43: https://help.zscaler.com/zpa/about-client-forwarding-policy | N43: Configuring Forwarding Profiles for Zscaler Client Connector — https://help.zscaler.com/zscaler-client-connector/configuring-forwarding-profiles-zscaler-client-connector Understanding the Private Access Architecture — https://help.zscaler.com/zpa/understanding-private-access-architecture Configuring Defined Application Segments — https://help.zscaler.com/zpa/configuring-defined-application-segments | O43: [About Client Forwarding Policy] “Private Access evaluates client forwarding policy rules using the most specific application segment and a top-down, first-match principle. This process occurs before Private Access evaluates access policy rules.” [About Client Forwarding Policy] “Indicates if the rule will Bypass ZPA, Only Forward Allowed Applications, or Forward to ZPA.” | P43: [About Client Forwarding Policy] “When a match is found in the client forwarding policy, Private Access disregards other policy rules, including conflicts.” [Configuring Defined Application Segments] “If there is no match in this application segment, Zscaler Client Connector bypasses Private Access and sends traffic directly.” | Q43: ~10 BYPASS rules, none with an expiry (README; T-054). Bypassed traffic never reaches access policy and leaves no user activity record, so each bypass silently removes a destination from discovery. | R43: 2026-10-20
A44: ZT-43 | B44: Element 3 — Where is the connection going? | C44: Connectivity | D44: Requirement | E44: Select the best path dynamically per application. | F44: “best-path selection to be determined per app” “dynamically determining the optimal path to each application in a secure manner” | G44: 61, 146 | H44: 63, 148 | I44: App Connector selection (Closer to User / Closer to Application) and health reporting | J44: By default ZPA picks the App Connector closest to the user; with Closer to Application it picks the one with the shortest round-trip time to the app. Health reporting (Continuous / On Access / None) tells ZPA which connectors can reach the app. How Client Connector chooses its Service Edge is not documented in the articles found. | K44: Partial | L44: Configuring Defined Application Segments | M44: https://help.zscaler.com/zpa/configuring-defined-application-segments | N44: Understanding Health Reporting — https://help.zscaler.com/zpa/understanding-health-reporting About App Connector Groups — https://help.zscaler.com/zpa/about-connector-groups | O44: [Configuring Defined Application Segments] “By default, Private Access chooses the App Connector as closest to the user (Closer to User).” [Configuring Defined Application Segments] “After you make a selection, Private Access selects an App Connector that has the shortest round-trip time towards the requested application.” | P44: [Configuring Defined Application Segments] “The limit for the number of targets that check the health of the defined applications at the App Connector is 6,000. If this limit is exceeded, then the Health Reporting of the application is set to None, and a random selection of App Connectors is chosen.” [Configuring Defined Application Segments] “To enable Closer to Application for UDP, contact Zscaler Support.” | R44: 2026-10-20
A45: ZT-44 | B45: Element 4 — Assess risk using context | C45: Risk | D45: Requirement | E45: Compute a dynamic risk score for the user/device (posture, threats, behaviour) and use the latest score in access decisions. | F45: “The solution must account for an enterprise’s tolerance for risk via a dynamic risk score.” “allowing enterprises to regulate access based on the latest, dynamically collected scores” | G45: 14, 72, 73, 74, 75, 76, 77 | H45: 16, 74, 75, 76, 77, 78, 79 | I45: Risk Scores criterion (user risk from Internet & SaaS); Adaptive Access profiles | J45: ZPA does not compute risk itself. Internet & SaaS calculates the user risk score and propagates it to Private Access, where Low / Medium / High / Critical can be used in access policy; Adaptive Access profiles can add third-party signals; Zscaler documents Adaptive Access Engine integrations for CrowdStrike and Microsoft Defender, among others. | K45: Other Zscaler product | L45: About User Risk Scores | M45: https://help.zscaler.com/zpa/about-user-risk-scores | N45: Understanding User Risk Score — https://help.zscaler.com/zia/understanding-user-risk-score Understanding Adaptive Access Engine — https://help.zscaler.com/unified/understanding-adaptive-access-engine About Adaptive Access Profiles — https://help.zscaler.com/unified/about-adaptive-access-profiles Integrating CrowdStrike with Adaptive Access Engine — https://help.zscaler.com/unified/integrating-crowdstrike-adaptive-access-engine Integrating Microsoft Defender with Adaptive Access Engine — https://help.zscaler.com/unified/integrating-microsoft-defender-adaptive-access-engine | O45: [About User Risk Scores] “You can add user risk scores as a criteria type to access policy rules.” [Understanding User Risk Score] “The User Risk Score computation happens in Internet & SaaS and then it is propagated to Private Access.” | P45: [About User Risk Scores] “User risk scores are not supported in User Portals or Privileged Remote Access Portals.” [Understanding Adaptive Access Engine] “Authentication Service for end users is enabled or end user migration to Authentication Service is completed.” | Q45: Inferred: a score exists only for users who authenticate to Internet & SaaS. Whether this tenant uses Internet & SaaS in production is not recorded in the README, discovery or decision notes (only the Splunk lab models ZIA). | R45: 2026-10-20
A46: ZT-45 | B46: Element 4 — Assess risk using context | C46: Risk | D46: Requirement | E46: Evaluate continuously: re-verify identity when the original authentication criteria no longer hold, update access in near real time on posture/behaviour change, and let the customer set evaluation frequency. | F46: “identity verification must be continuously updated in the event the original authentication criteria are no longer met” “Customers must also decide on the frequency with which this determination must be made” | G46: 73, 75, 113, 134 | H46: 75, 77, 115, 136 | I46: Timeout policy (re-authentication and idle timeouts); posture re-evaluation; SCIM deprovisioning | J46: ZPA re-evaluates at new connections, not mid-session. Posture is re-checked every 2–15 minutes (EDR and process checks immediately on change), but existing connections are unaffected; the authentication timeout forces re-authentication at the next access attempt; SCIM removes deleted or disabled users. No documented control ends an open session when posture or risk changes. The two timeout articles disagree on the default idle timeout (never vs 2 hours). | K46: Partial | L46: About Device Posture Profiles | M46: https://help.zscaler.com/zscaler-client-connector/about-device-posture-profiles | N46: About Timeout Policy — https://help.zscaler.com/zpa/about-timeout-policy Configuring Timeout Policies — https://help.zscaler.com/zpa/configuring-timeout-policies About SCIM — https://help.zscaler.com/zpa/about-scim Configuring Device Posture Profiles — https://help.zscaler.com/zscaler-client-connector/configuring-device-posture-profiles | O46: [About Device Posture Profiles] “Zscaler Client Connector evaluates device posture profiles every 15 minutes. New connections are established based on updated security postures. Existing connections are not affected by updates to security postures.” [About Timeout Policy] “It is only evaluated when a user attempts to access an application. After a user's session has expired for a specific application, the user is only prompted to reauthenticate at the next attempt to access that application.” | P46: [About Timeout Policy] “The option to enable or disable termination of all running application sessions upon timeout is available only for existing tenants. This option is hidden and automatically enabled for tenants created after November 3, 2022.” [Configuring Timeout Policies] “The Authentication Timeout must be at least 10 minutes.” [Configuring Timeout Policies] “For an open TCP session, the timeout is 2 hours.” | Q46: Timeout policy is part of phase 5 policy design (README). Test before relying on it: open a session, fail posture (e.g. stop EDR), and see whether the session survives; read ConnectionStatus and InternalReason in user activity. | R46: 2026-10-20
A47: ZT-46 | B47: Element 5 — Prevent compromise | C47: Inspection | D47: Requirement | E47: Inspect traffic to internal (private) web applications, including TLS-encrypted traffic, even after the user and risk have been verified. | F47: “HTTP-based services must be inspected even after a valid user and acceptable risk score have been verified.” “Inspection of both external and internal application access is critical since both traffic flows may be encrypted.” | G47: 84, 92, 96 | H47: 86, 94, 98 | I47: AppProtection (inline inspection of private web apps, including HTTPS) | J47: AppProtection policy inspects traffic to internal web applications, selected by criteria such as application segment, posture and SAML/SCIM attributes; HTTPS is inspected using certificates configured for the AppProtection application. AppProtection also lists API and Active Directory controls, and LSS has KRB, LDAP and SMB Inspection log types — inspection beyond web apps exists but is not mapped here. | K47: Native | L47: About AppProtection Policy | M47: https://help.zscaler.com/zpa/about-appprotection-policy | N47: About AppProtection Applications — https://help.zscaler.com/zpa/about-appprotection-applications About Applications — https://help.zscaler.com/zpa/about-applications About AppProtection Controls — https://help.zscaler.com/zpa/about-appprotection-controls About the Log Streaming Service — https://help.zscaler.com/zpa/about-log-streaming-service | O47: [About AppProtection Policy] “Create a policy to inspect traffic to internal web applications based on specific criteria (e.g., application segments, Client Connector posture profiles, and SAML and SCIM attributes).” [About AppProtection Applications] “Configure HTTP/S ports and provide certificates for inspection of encrypted traffic.” | P47: [About Applications] “Apply advanced capabilities that you are licensed for such as Browser Access, Zero Trust Browser, AppProtection, and data loss prevention.” [About AppProtection Policy] “Depending on your AppProtection subscription, you see the following Security policy option: Browser Protection.” | Q47: Not in the current design; AppProtection sits on learning track 5 (README). | R47: 2026-10-20
A48: ZT-47 | B48: Element 5 — Prevent compromise | C48: Inspection | D48: Requirement | E48: Shield private applications from web attacks such as the OWASP Top 10 and block them inline. | F48: “such as OWASP Top 10 attacks” | G48: 96, 97, 116 | H48: 98, 99, 118 | I48: AppProtection predefined OWASP controls; Recommended OWASP Top 10 profile | J48: AppProtection profiles apply predefined OWASP controls (SQL injection, XSS and more); a ‘Recommended OWASP Top 10 Profile’ is supplied, and each control’s action is Allow, Block or Redirect. | K48: Native | L48: About AppProtection Controls | M48: https://help.zscaler.com/zpa/about-appprotection-controls | N48: About AppProtection Profiles — https://help.zscaler.com/zpa/about-appprotection-profiles About AppProtection Policy — https://help.zscaler.com/zpa/about-appprotection-policy | O48: [About AppProtection Controls] “Protect internal applications from all types of attacks in the OWASP predefined controls with SQL injection, cross-site scripting (XSS), and more.” [About AppProtection Profiles] “It is named Recommended OWASP Top 10 Profile in the AppProtection profile table.” | R48: 2026-10-20
A49: ZT-48 | B49: Element 5 — Prevent compromise | C49: Inspection | D49: Requirement | E49: Protect against known CVEs and allow customised rules for enterprise-specific environments. | F49: “the ability to build customized rules to protect enterprise-specific environments” | G49: 96, 97 | H49: 98, 99 | I49: AppProtection ThreatLabZ (CVE) controls and custom controls | J49: ThreatLabZ predefined controls address confirmed CVEs; custom controls match chosen request and response elements (headers, body, etc.) and apply a chosen action. | K49: Native | L49: About ThreatLabZ Controls | M49: https://help.zscaler.com/zpa/about-threatlabz-controls | N49: About Custom Controls — https://help.zscaler.com/zpa/about-custom-controls | O49: [About ThreatLabZ Controls] “The ThreatLabZ predefined controls in the Zscaler Admin Console are created by the Zscaler Security team to address confirmed Common Vulnerabilites and Exposures (CVEs). [sic]” [About Custom Controls] “Custom controls give you the flexibility to set and define the specific request and response elements (e.g., request header, response body, etc.) and the preferred action used to handle them.” | R49: 2026-10-20
A50: ZT-49 | B50: Element 5 — Prevent compromise | C50: Inspection | D50: Requirement | E50: Apply inspection per application segment, so Segment A can carry different controls from Segment B. | F50: “inspection for attacks on Segment A may differ from the inspection controls of Segment B” | G50: 97 | H50: 99 | I50: AppProtection policy rules with application-segment criteria and per-rule profiles | J50: Profiles are applied through AppProtection policy rules whose criteria include application segments, so different segments can carry different profiles (one rule per segment set that needs its own profile). | K50: Native | L50: About AppProtection Policy | M50: https://help.zscaler.com/zpa/about-appprotection-policy | N50: About AppProtection Profiles — https://help.zscaler.com/zpa/about-appprotection-profiles | O50: [About AppProtection Policy] “Apply a previously created AppProtection profile to a policy with the default actions (Allow, Block, or Redirect) set for each related AppProtection control.” | R50: 2026-10-20
A51: ZT-50 | B51: Element 5 — Prevent compromise | C51: Inspection | D51: Requirement | E51: Decide inspection granularly (not inspect-all or inspect-nothing): bypass traffic that cannot or should not be inspected (pinned certificates, real-time media), balancing protection and privacy. | F51: “not as a binary “inspect or don’t inspect” policy” “Enterprises must consider that not all traffic types can be, or should be, inspected.” | G51: 15, 85, 90, 92 | H51: 17, 87, 92, 94 | I51: AppProtection policy actions: Inspect / Bypass Inspection | J51: Each AppProtection rule either inspects or bypasses inspection for matching traffic, so inspection can be scoped by segment, user and posture. | K51: Native | L51: About AppProtection Policy | M51: https://help.zscaler.com/zpa/about-appprotection-policy | N51: About AppProtection Applications — https://help.zscaler.com/zpa/about-appprotection-applications | O51: [About AppProtection Policy] “Rule Action: Indicates if the rule is to Inspect or Bypass Inspection.” | R51: 2026-10-20
A52: ZT-51 | B52: Element 5 — Prevent compromise | C52: Inspection | D52: Requirement | E52: Use inspection of internal traffic to detect compromised or malicious user accounts (authorised users should not be attacking internal services). | F52: “detecting compromised or malicious user accounts, since authorized users or devices should not be attacking internal services” | G52: 97 | H52: 99 | I52: AppProtection log type via LSS to the SIEM | J52: AppProtection logs control hits, and LSS streams the AppProtection log type to the SIEM; correlating attacks with the authenticated user is SIEM work, not a ZPA feature. The log fields still use the legacy ‘Inspection’ names. | K52: Partial | L52: Understanding AppProtection Log Fields | M52: https://help.zscaler.com/zpa/understanding-appprotection-log-fields | N52: About the Log Streaming Service — https://help.zscaler.com/zpa/about-log-streaming-service | O52: [Understanding AppProtection Log Fields] “By default, the AppProtection log type includes the fields listed in the table below for each log template (i.e., CSV, JSON, TSV).” | Q52: AppProtection is not among the LSS streams in the README. Pin its field names from Understanding AppProtection Log Fields (they keep the legacy Inspection names) before writing SPL. | R52: 2026-10-20
A53: ZT-52 | B53: Element 6 — Prevent data loss | C53: Data protection | D53: Requirement | E53: Extend inline data loss prevention to traffic to internal applications. | F53: “However, the same protections should be extended to internal application access.” | G53: 96, 100, 105 | H53: 98, 102, 107 | I53: Zero Trust Browser isolation profile forwarding private-app traffic through Internet & SaaS DLP | J53: No DLP built into ZPA was found. The documented route is to isolate the private web app with Zero Trust Browser and enable, per isolation profile, forwarding of that traffic through Internet & SaaS so its DLP and security policies apply. It covers isolated (Web Browser) sessions only; Client Connector traffic gets no inline DLP this way. | K53: Partial | L53: Forwarding Traffic from Private Access Profiles to Internet & SaaS in Isolation | M53: https://help.zscaler.com/zero-trust-browser/forwarding-traffic-from-private-access-to-internet-and-saas-profiles-in-isolation | N53: About Isolation Policy — https://help.zscaler.com/zpa/about-isolation-policy About AppProtection Controls — https://help.zscaler.com/zpa/about-appprotection-controls | O53: [Forwarding Traffic from Private Access Profiles to Internet & SaaS in Isolation] “Users who isolate private web applications might also want to enforce DLP policies or security policies on the traffic.” [Forwarding Traffic from Private Access Profiles to Internet & SaaS in Isolation] “Zero Trust Browser can forward the private application traffic via Internet & SaaS ensuring that all these policies are applied.” [Forwarding Traffic from Private Access Profiles to Internet & SaaS in Isolation] “You can enable this feature per Private Access isolation profile.” | P53: [Forwarding Traffic from Private Access Profiles to Internet & SaaS in Isolation] “However, an isolation browser initiated from Private Access policies can send traffic only via Private Access.” [Forwarding Traffic from Private Access Profiles to Internet & SaaS in Isolation] “It can also ensure that Internet & SaaS provides connectivity to the private applications via the Source IP Anchoring route.” | Q53: Closed here: the route depends on isolation, which needs the Web Browser client type, i.e. Browser Access — out of scope (decision 2026-09-27). | R53: 2026-10-20
A54: ZT-53 | B54: Element 6 — Prevent data loss | C54: Data protection | D54: Requirement | E54: Isolate sessions (stream pixels) so private application data cannot be downloaded to, copied to or persist on unmanaged or untrusted devices. | F54: “enables access to private data without allowing the data to persist on the device by streaming pixels” “restricts the ability to download, copy and paste data” | G54: 23, 43, 105, 110, 114, 119, 130 | H54: 25, 45, 107, 112, 116, 121, 132 | I54: Isolation policy for Private Access (Zero Trust Browser) with isolation profiles | J54: Isolation policy redirects matching private web-app requests to a containerised browser in the Zscaler cloud that renders the page remotely and streams it to the user; profiles stop copy, paste, upload and download and can be read-only. Rules require the Web Browser client type — Client Connector posture, trusted networks and machine groups are not supported as criteria. | K54: Other Zscaler product | L54: About Isolation Policy | M54: https://help.zscaler.com/zpa/about-isolation-policy | N54: Configuring Isolation Policies — https://help.zscaler.com/zpa/configuring-isolation-policies About Isolation Profiles for Private Access — https://help.zscaler.com/zero-trust-browser/about-isolation-profiles-private-access Understanding Cloud Browser — https://help.zscaler.com/zero-trust-browser/understanding-cloud-browser Read-Only Mode in Isolation — https://help.zscaler.com/zero-trust-browser/read-only-mode-isolation | O54: [About Isolation Policy] “Enforce data exfiltration controls by ensuring users are unable to copy, paste, upload, or download files between their computers and the applications they are accessing.” [Configuring Isolation Policies] “The Web Browser client type is required for isolation policy rules, and it is the only client type available.” | P54: [About Isolation Policy] “This requires having isolation enabled for your organization and creating an isolation profile prior to setting up the isolation policy rule.” [About Isolation Policy] “Along with defining an isolation policy, you also need to define an access policy for the application to be accessible from within the browser isolation environment.” [Configuring Isolation Policies] “The Client Connector Posture Profiles, Client Connector Trusted Networks, and the Machine Groups criteria may appear in the drop-down menu, but they are not supported with Web Browser client type, which is required for isolation policies.” | Q54: Closed here: isolation rules need the Web Browser client type, i.e. Browser Access — out of scope (decision 2026-09-27). Unavailable unless that decision is revisited. | R54: 2026-10-20
A55: ZT-54 | B55: Element 7 — Enforce policy | C55: Enforcement | D55: Requirement | E55: Decide per session using every earlier output — identity, context, destination, risk, malicious content, data loss; tear the connection down at session end and re-evaluate the next request. | F55: “Policy enforcement must take into consideration all previously validated qualities” “for subsequent requests, the process begins again” | G55: 15, 113, 116, 133, 134 | H55: 17, 115, 118, 135, 136 | I55: Per-request policy evaluation across access, timeout, client forwarding, isolation and AppProtection policies | J55: Each application request is evaluated against policy (most specific segment, top-down, first match) using identity, posture, network, client type, country and risk score; new connections pick up changed posture. Content (AppProtection) and data (isolation) controls are separate policies applied only where configured, not inputs to one combined decision. | K55: Partial | L55: Understanding Policies | M55: https://help.zscaler.com/zpa/understanding-policies | N55: About Access Policy — https://help.zscaler.com/zpa/about-access-policy About Device Posture Profiles — https://help.zscaler.com/zscaler-client-connector/about-device-posture-profiles About AppProtection Policy — https://help.zscaler.com/zpa/about-appprotection-policy About Isolation Policy — https://help.zscaler.com/zpa/about-isolation-policy | O55: [Understanding Policies] “Private Access evaluates policy rules using the most specific application segment and a top-down, first-match principle.” [About Device Posture Profiles] “New connections are established based on updated security postures.” | R55: 2026-10-20
A56: ZT-55 | B56: Element 7 — Enforce policy | C56: Enforcement | D56: Requirement | E56: Offer conditional allow outcomes beyond plain allow — allow with isolation, inspection or a warning to the user. | F56: “with the ability to deliver additional controls, such as isolation, inspection, and warnings” | G56: 114, 116, 119 | H56: 116, 118, 121 | I56: Access policy actions (Allow / Block / Conditional Access) plus isolation and AppProtection policies | J56: Allow can be paired with isolation (Web Browser sessions) and AppProtection inspection through their own policies; Conditional Access adds step-up authentication (Authentication Service). No ‘warn’ action is documented for Private Access. The help centre is inconsistent on actions: About Access Policy lists Require Approval, Configuring Access Policies lists Conditional Access and a PRA-only privileged-approval option. | K56: Partial | L56: Configuring Access Policies | M56: https://help.zscaler.com/zpa/configuring-access-policies | N56: About Access Policy — https://help.zscaler.com/zpa/about-access-policy About Privileged Approvals — https://help.zscaler.com/zpa/about-privileged-approvals About Isolation Policy — https://help.zscaler.com/zpa/about-isolation-policy About AppProtection Policy — https://help.zscaler.com/zpa/about-appprotection-policy | O56: [Configuring Access Policies] “Allow Access: Allows access to applications.” [Configuring Access Policies] “Block Access: Blocks access to applications.” [Configuring Access Policies] “Conditional Access: Allows access to sensitive resources for step-up authentication, and is only an option if you are subscribed to Authentication Service.” [About Access Policy] “Rule Action: Indicates if the rule will Allow Access, Block Access, or Require Approval.” | P56: [Configuring Access Policies] “The Allow with Privileged Approval checkbox is only an option if you have Privileged Remote Access (PRA) and is primarily targeted for PRA-enabled application segments. Contact Zscaler Support for more information.” | R56: 2026-10-20
A57: ZT-56 | B57: Element 7 — Enforce policy | C57: Enforcement | D57: Requirement | E57: Steer traffic so that services requiring a known or geo-specific source IP see the organisation's anchored egress address. | F57: “This could be for leveraging an anchored IP address for geo-specific solutions or sending traffic through a more effective path.” | G57: 114, 119, 120, 127 | H57: 116, 121, 122, 129 | I57: Source IP Anchoring (Internet & SaaS forwarding through ZPA App Connectors) | J57: Internet & SaaS forwarding policy steers selected traffic through ZPA App Connectors, so the destination sees the App Connector’s IP — an address the organisation chooses. ZPA side: the Source IP Anchor option on the segment, client forwarding policy, and access rules for the Internet & SaaS Service Edge client type. | K57: Other Zscaler product | L57: Understanding Source IP Anchoring | M57: https://help.zscaler.com/zia/understanding-source-ip-anchoring | N57: Configuring Source IP Anchoring — https://help.zscaler.com/zia/configuring-source-ip-anchoring Configuring Defined Application Segments — https://help.zscaler.com/zpa/configuring-defined-application-segments | O57: [Understanding Source IP Anchoring] “Forwarding policies for Source IP Anchoring allow organizations to steer selective traffic processed by Internet & SaaS (ZIA) to the internal or external destination servers of their choice. This ensures that Zscaler secures the traffic and that the source IP address is the organization's choice.” [Understanding Source IP Anchoring] “The source IP address of the traffic reaching the destination is the IP address of the Private Access (ZPA) App Connector deployed as part of Source IP Anchoring.” | P57: [Understanding Source IP Anchoring] “You don't need a Private Access license to access the Source IP Anchoring feature. However, a Source IP Anchoring subscription is required. For more information, contact Zscaler Support.” [Understanding Source IP Anchoring] “Source IP Anchoring does not support the Real Time Streaming Protocol (RTSP).” [Configuring Defined Application Segments] “If you selected Browser Access or Source IP Anchoring for any application, you can't enable Double Encryption.” | Q57: Source IP anchoring sits on learning track 5 (README). | R57: 2026-10-20
A58: ZT-57 | B58: Element 7 — Enforce policy | C58: Enforcement | D58: Requirement | E58: Apply the same, centrally defined policy uniformly at every enforcement point (Zscaler-hosted or customer-hosted), independent of where initiator and application sit. | F58: “Policy enforcement must be constantly and uniformly applied.” “applies the same policies as the public service edge” | G58: 115, 124, 126, 132, 138, 139 | H58: 117, 126, 128, 134, 140, 141 | I58: One central policy enforced by Public and Private Service Edges | J58: Public Service Edges enforce access and re-authentication policy; Private Service Edges download the tenant’s policies and enforce all Private Access policies, so one policy set applies wherever a session is brokered. Exception: Disaster Recovery mode lists ‘Policies’ and ‘Log Streaming Service’ as not supported. | K58: Native | L58: About Private Service Edges | M58: https://help.zscaler.com/zpa/about-private-service-edges | N58: Understanding Service Edges — https://help.zscaler.com/zpa/understanding-service-edges Understanding Disaster Recovery — https://help.zscaler.com/zpa/understanding-disaster-recovery | O58: [About Private Service Edges] “This allows a Private Service Edge to download the relevant policies and configurations so it can enforce all Private Access policies.” [Understanding Service Edges] “Public Service Edges enforce access and reauthentication policies based on your organization's corporate best practices.” | Q58: The PSE and the public service edges run one policy, but PSE health is invisible in Splunk (decision 2026-09-19). | R58: 2026-10-20
A59: ZT-58 | B59: Connecting to the Applications | C59: Connectivity | D59: Requirement | E59: Connect to internal apps inside-out only: a connector next to the application dials out to the broker, the initiator dials out too, and the broker stitches the two per-session encrypted connections; no inbound connections to internal apps. | F59: “These App Connectors provide the outbound-only connection from the app environment to the broker function within the appropriate Zero Trust Exchange Service Edge.” “No inbound connections to internally managed apps are permitted.” | G59: 23, 24, 124, 128, 133, 145 | H59: 25, 26, 126, 130, 135, 147 | I59: App Connectors (outbound-only) brokered by Public/Private Service Edges | J59: App Connectors sit next to (or with reach to) applications and connect outbound only to Service Edges; Client Connector holds TLS-encrypted tunnels to the Service Edge too, and the Service Edge brokers the two per application. App Connectors never accept inbound connections or talk to each other. Traffic is decrypted in Service Edge memory unless Double Encryption is enabled (ZT-66). | K59: Native | L59: About App Connectors | M59: https://help.zscaler.com/zpa/about-connectors | N59: Understanding the Private Access Architecture — https://help.zscaler.com/zpa/understanding-private-access-architecture What Is Zscaler Private Access? — https://help.zscaler.com/zpa/what-zscaler-private-access Private Service Edge Deployment Prerequisites — https://help.zscaler.com/zpa/service-edge-deployment-prerequisites | O59: [About App Connectors] “App Connectors only connect outbound; they do not need any inbound open ports to operate correctly.” [About App Connectors] “App Connectors can be co-located with your enterprise applications, or they can be deployed in any location that has connectivity to the applications.” [Understanding the Private Access Architecture] “App Connectors never communicate with each other and do not accept inbound connections.” | P59: [Private Service Edge Deployment Prerequisites] “Your firewalls must be configured to let the Private Service Edge establish outbound connections to the IP addresses of the Public Service Edge for Private Access, and establish inbound connections from App Connectors and Zscaler Client Connector.” | Q59: Glossary ‘Egress’: an App Connector in a tightly egress-filtered segment cannot dial out. Glossary ‘ACL’: apps see the connector’s address, not the user’s. | R59: 2026-10-20
A60: ZT-59 | B60: Connecting to the Applications | C60: Connectivity | D60: Requirement | E60: Apply zero trust 'within the four walls': on-premises users are brokered by an enforcement point deployed locally (traffic stays local, apps are not discoverable on the LAN, lower latency). | F60: “can also be run locally within individual customer locations for seamless deployment of the zero trust controls” “This deployment model allows zero trust within the four walls” | G60: 22, 46, 129, 138, 139, 140 | H60: 24, 48, 131, 140, 141, 142 | I60: Private Service Edges | J60: A Private Service Edge is a single-tenant broker hosted in the customer’s data centre or cloud; it downloads the tenant’s policies and enforces all Private Access policies locally, so on-site users are brokered inside the customer’s environment. | K60: Native | L60: About Private Service Edges | M60: https://help.zscaler.com/zpa/about-private-service-edges | N60: Private Service Edge Deployment Prerequisites — https://help.zscaler.com/zpa/service-edge-deployment-prerequisites Understanding the Private Access Architecture — https://help.zscaler.com/zpa/understanding-private-access-architecture | O60: [About Private Service Edges] “Private Service Edges for Private Access (ZPA) are single-tenant instance brokers that provide the functionality of a Public Service Edge for Private Access in an organization’s environment.” [About Private Service Edges] “This allows a Private Service Edge to download the relevant policies and configurations so it can enforce all Private Access policies.” | P60: [Private Service Edge Deployment Prerequisites] “Each Private Service Edge supports up to 500 Mbps of throughput.” [Private Service Edge Deployment Prerequisites] “Because the service enforces TLS certificate pinning for both client and server certificates, all forms of inline or man-in-the-middle TLS interception or inspection must be disabled.” [Private Service Edge Deployment Prerequisites] “Your firewalls must be configured to let the Private Service Edge establish outbound connections to the IP addresses of the Public Service Edge for Private Access, and establish inbound connections from App Connectors and Zscaler Client Connector.” | Q60: One PSE serves the SYDNEY LAN and carries most business traffic; its status log is not streamed (decision 2026-09-19); whether PSE-brokered sessions appear in user activity is unconfirmed (T-042). Inferred: at up to 500 Mbps per PSE, one PSE is a capacity and single-point-of-failure question; and ZPA removes no LAN route — apps are ‘not discoverable on the network’ only where direct paths are closed. | R60: 2026-10-20
A61: ZT-60 | B61: Connecting to the Applications | C61: Segmentation | D61: Requirement | E61: Choose connector scope per need: dedicated to one application, shared by a group of applications or sites, or spanning peered environments (the last mainly during early discovery). | F61: “the Zero Trust Exchange allows enterprises to be as refined as needed with their connection controls” “This strategy is often used during the early discovery phase of a zero trust deployment.” | G61: 131 | H61: 133 | I61: App Connector groups and server groups | J61: A segment’s server group names the App Connector groups allowed to reach its servers, so connector scope can be one app, a site or set of apps, or several environments; App Connectors should only be assigned to applications they can actually reach. | K61: Native | L61: About Server Groups | M61: https://help.zscaler.com/zpa/about-server-groups | N61: About App Connector Groups — https://help.zscaler.com/zpa/about-connector-groups About App Connectors — https://help.zscaler.com/zpa/about-connectors | O61: [About Server Groups] “When configuring an application segment within Private Access (ZPA), you must identify the server group that contains the servers hosting the defined applications.” [About App Connector Groups] “App Connector groups must be associated with applications that the App Connector can access (i.e., only assign App Connectors to applications that the App Connector is capable of reaching).” | P61: [About Server Groups] “You can create a server group with Dynamic Server Discovery enabled so that Private Access discovers the appropriate servers for your applications as users request them.” | Q61: README lever: Server + App Connector Group tight = one per trust zone; loose = one shared group for everything. Inferred: whatever an App Connector can reach on the network is the effective boundary of every segment it serves. | R61: 2026-10-20
A62: ZT-61 | B62: Connecting to the Applications | C62: Logging & visibility | D62: Requirement | E62: Stream logs securely to the SIEM/SOAR, giving per-access-request visibility (who accessed which application) rather than IP-to-IP flows. | F62: “The logging plane is where configuration takes place and logs are securely streamed to a SIEM/SOAR.” “Provides granular visibility and learning of flows per access request, not network IP-to-IP” | G62: 52, 132, 146 | H62: 54, 134, 148 | I62: Log Streaming Service (LSS) with log receivers | J62: LSS streams per-session User Activity plus User Status, App Connector, Private Service Edge, Audit, AppProtection, Browser Access and other log types from an App Connector to a log receiver that feeds the SIEM. Data generated while the App Connector is cut off is not sent, and the 15-minute resend is not guaranteed. | K62: Native | L62: About the Log Streaming Service | M62: https://help.zscaler.com/zpa/about-log-streaming-service | N62: Configuring a Log Receiver — https://help.zscaler.com/zpa/configuring-log-receiver Understanding User Activity Log Fields — https://help.zscaler.com/zpa/understanding-user-activity-log-fields | O62: [About the Log Streaming Service] “LSS is deployed using two components: a log receiver and an App Connector.” [About the Log Streaming Service] “The LSS does not transmit any log data generated during a connection loss between Private Access and the App Connectors. After the connection is restored, it can retransmit the last 15 minutes of the log data. However, the delivery of that log data is not guaranteed.” | P62: [About the Log Streaming Service] “Zscaler retains User Activity, User Status, and App Connector log information for rolling periods of at least 14 days during the subscription term. Zscaler retains audit log information for at least 6-month periods during the subscription term.” [Configuring a Log Receiver] “If the FQDN or IP address of the log receiver overlaps with or is the same as the wildcard domain or IP subnet defined in an application segment, the Bypass setting configured for the application segment takes precedence.” | Q62: LSS → Splunk: user activity, user status, App Connector status, connector metrics and audit logs stream; Browser Access does not (out of scope); PSE status not configured (README). Check the log receiver’s FQDN/IP is not inside as-CatchAll (*.example.com) — an overlap hands delivery to the segment’s Bypass setting. Delivery gaps show only as missing time: discovery-window-continuity.spl is the guard. | R62: 2026-10-20
A63: ZT-62 | B63: Connecting to the Applications | C63: Workload & IoT/OT | D63: Requirement | E63: Segment workload-to-workload (east-west) traffic with identity-based, process-level microsegmentation. | F63: “Identity-based microsegmentation (process-level)” “finally with workload-to-workload, identity-based microsegmentation” | G63: 18, 46, 124, 147 | H63: 20, 48, 126, 149 | I63: Zscaler Microsegmentation (agent-based east-west platform) | J63: A separate platform in the Zscaler Admin Console: agents on Windows and Linux hosts collect flows and enforce policy through the host firewall (Windows Filtering Platform, nftables), with recommendations from 14 days of flows. The articles describe host- and flow-based segmentation; they do not call it process- or identity-based. | K63: Other Zscaler product | L63: What Is Microsegmentation? | M63: https://help.zscaler.com/zpa/what-is-microsegmentation | N63: About Policy Recommendations for Resource Groups — https://help.zscaler.com/zpa/about-policy-recommendations-resource-groups | O63: [What Is Microsegmentation?] “Zscaler Microsegmentation is a platform within the Zscaler Admin Console that provides the capability to visualize traffic flows within private applications and segment them on a fractional level, reducing the attack surface and preventing lateral movement of any threats on your network.” [About Policy Recommendations for Resource Groups] “Review policy recommendations for a resource group based on flows from the last 14 days.” | P63: [What Is Microsegmentation?] “If you want Microsegmentation provisioned for your organization, contact your Zscaler Account team.” [What Is Microsegmentation?] “Microsegmentation agents and Zscaler Client Connector are not compatible and should not be installed on the same host.” [What Is Microsegmentation?] “The backend application is hosted and managed by the Zscaler cloud and is available across the US region.” | Q63: Out of scope until user-to-app cutover (T-022) or a PCI DSS finding requires the CDE to be isolated (T-010) (decision 2026-09-19). The Microsegmentation backend is stated as ‘available across the US region’ — a data-residency check for a Sydney-based estate before revisiting. | R63: 2026-10-20
A64: ZT-63 | B64: Fast, reliable, easy to operate | C64: Resilience | D64: Requirement | E64: Deliver enforcement from globally distributed, SLA-backed service edges, with public evidence of availability and scale. | F64: “Supported with a valid SLA.” | G64: 136, 137, 140, 143 | H64: 138, 139, 142, 145 | I64: Public Service Edges in Zscaler data centres; published IP ranges (config.zscaler.com) | J64: Public Service Edges run in Zscaler data centres worldwide at very large concurrency. Firewall ranges are published on config.zscaler.com, and Zscaler gives 90 days’ notice before activating new IP ranges. The SLA itself is contractual — no help-centre article states it. | K64: Not in help centre | L64: Understanding Service Edges | M64: https://help.zscaler.com/zpa/understanding-service-edges | N64: Zscaler Config — https://config.zscaler.com/private.zscaler.com/zpa Private Service Edge Deployment Prerequisites — https://help.zscaler.com/zpa/service-edge-deployment-prerequisites | O64: [Understanding Service Edges] “Public Service Edges for Private Access (ZPA), addressed here, are deployed in Zscaler data centers around the world and can handle hundreds of thousands of concurrent users with millions of concurrent sessions.” [Private Service Edge Deployment Prerequisites] “Zscaler's policy is to provide a 90-day notice for activating additional IP CIDR ranges to provide organizations with sufficient opportunity for changing control policies.” | P64: [Zscaler Config] “It is important to note that the full set of ZPA-enabled data centers must be allowed, as a partial firewall configuration will result in connectivity problems for end users.” | Q64: Confirm which Zscaler cloud the tenant is on (private.zscaler.com or zpatwo.net); it decides which published ranges the PSE and App Connector firewalls must allow (Private Service Edge Deployment Prerequisites). | R64: 2026-10-20
A65: ZT-64 | B65: Fast, reliable, easy to operate | C65: Resilience | D65: Requirement | E65: A locally deployed enforcement point should keep private application access working if the internet connection is lost. | F65: “This option also provides a layer of survivability if a connection to the internet is lost.” | G65: 139 | H65: 141 | I65: Business Continuity (Private Cloud Controllers); Disaster Recovery mode | J65: Business Continuity keeps users reaching apps through Private Access cloud or ISP outages: App Connectors and Private Service Edges fall back to customer-run Private Cloud Controllers, which hold a full copy of configuration and policy. Disaster Recovery is a separate mode the admin triggers by publishing DNS TXT records; it lists policies and log streaming as not supported. | K65: Native | L65: Understanding Business Continuity | M65: https://help.zscaler.com/zpa/understanding-business-continuity | N65: About Private Cloud Controllers — https://help.zscaler.com/zpa/about-private-cloud-controllers Understanding Disaster Recovery — https://help.zscaler.com/zpa/understanding-disaster-recovery | O65: [Understanding Business Continuity] “Business Continuity for Private Access (ZPA) allows users to continue to access applications during Private Access-related cloud outages or Internet Service Provider (ISP) outages.” [Understanding Business Continuity] “App Connectors and Private Service Edges leverage Private Clouds and Private Cloud Controllers when the Private Access cloud is not available or reachable.” [About Private Cloud Controllers] “Downloads and persists a complete copy of customer configuration and policies.” | P65: [Understanding Business Continuity] “End users' machines are running Zscaler Client Connector versions 4.6 and later for Windows.” [Understanding Business Continuity] “Browser Access, Source IP Anchoring, Cloud Connector, and Branch Connector client types are not supported.” [Understanding Business Continuity] “While in active Business Continuity, configuration changes (including deployment of Private Service Edges and App Connectors) are not supported.” [About Private Cloud Controllers] “To provide application access during a global Private Access outage, you must configure, enroll, and maintain Private Cloud Controllers.” [Understanding Disaster Recovery] “Activating disaster recovery by uploading the DNS TXT records to the Disaster Recovery Domain Name in the settings disrupts existing Zscaler Client Connector connections and must be used with caution.” | Q65: Decision 2026-09-19: whether sessions fall back to the public cloud when the PSE is unavailable is [unverified] for this tenant. The README, discovery and decision notes do not mention Business Continuity. Open: its documented client prerequisite names Windows only — confirm macOS and mobile with Zscaler. | R65: 2026-10-20
A66: ZT-65 | B66: Fast, reliable, easy to operate | C66: Operations | D66: Requirement | E66: Deploy and update the endpoint agent through endpoint managers, with centrally pushed policy changes. | F66: “Deployment of an agent through endpoint managers” | G66: 136, 140 | H66: 138, 142 | I66: Client Connector silent deployment through endpoint managers (e.g. Microsoft Intune) | J66: Once settings and policies are configured in the Admin Console, Client Connector can be deployed silently on Windows and macOS; Zscaler documents Intune deployment (macOS article found; a Windows/SCCM article was not found in this check). | K66: Native | L66: Deploying Zscaler Client Connector with Microsoft Intune for macOS | M66: https://help.zscaler.com/zscaler-client-connector/deploying-zscaler-client-connector-microsoft-intune-macos | N66: What Is Zscaler Client Connector? — https://help.zscaler.com/zscaler-client-connector/what-is-zscaler-client-connector | O66: [What Is Zscaler Client Connector?] “After you configure settings and policies in the Zscaler Admin Console, you can silently deploy the app on users' devices for Windows and macOS.” [Deploying Zscaler Client Connector with Microsoft Intune for macOS] “With Microsoft Intune, you can deploy Zscaler Client Connector for your macOS devices.” | P66: [Deploying Zscaler Client Connector with Microsoft Intune for macOS] “To deploy Zscaler Client Connector using the Microsoft Intune admin center, you must obtain a .pkg file from the Zscaler Admin Console.” | R66: 2026-10-20
A67: ZT-66 | B67: Fast, reliable, easy to operate | C67: Architecture | D67: Requirement | E67: Protect tenancy: customer data is not passed to other components and is never stored to disk. | F67: “Able to deliver tenancy protection so customer data privacy is not passed to any other component within the infrastructure and no data is ever stored to disk.” | G67: 12, 140 | H67: 14, 142 | I67: Service Edge traffic handling (memory only); Double Encryption; single-tenant Private Service Edges | J67: Zscaler states Private Access traffic is never written to disk at the Service Edge, but standard traffic is not encrypted while in Service Edge memory; Double Encryption adds an inner layer so it stays encrypted in transit through the edge. Multi-tenant isolation beyond this is a contractual and assurance matter, not in the help centre. | K67: Partial | L67: Understanding Double Encryption | M67: https://help.zscaler.com/zpa/understanding-double-encryption | N67: Understanding Service Edges — https://help.zscaler.com/zpa/understanding-service-edges About Private Service Edges — https://help.zscaler.com/zpa/about-private-service-edges | O67: [Understanding Double Encryption] “However, standard Private Access application traffic is not encrypted by Zscaler as it transits the Public Service Edge or Private Service Edge in memory, and is never written to disk.” [Understanding Double Encryption] “Enabling double encryption when defining an application allows an organization to add an additional layer of encryption inside the outer TLS tunnels, so that traffic is encrypted in memory as it transits the Public Service Edge or Private Service Edge.” [Understanding Service Edges] “In Private Access, the Service Edge does not inspect the data as traffic flows through it.” | P67: [Understanding Double Encryption] “Typically, this means the traffic counts double against the App Connector's capacity, versus standard Private Access traffic.” [Understanding Double Encryption] “Double encryption fails if the certificate of a client and a certificate of an App Connector do not share a common root CA.” [Understanding Double Encryption] “Double encryption is recommended only for sensitive data transmitted over unencrypted protocols (e.g., HTTP, FTP, telnet, etc.).” | Q67: Telnet is one of Zscaler’s named cases for Double Encryption, at double App Connector load; it applies at domain level (Understanding Double Encryption). | R67: 2026-10-20
A68: ZT-67 | B68: Fast, reliable, easy to operate | C68: Operations | D68: Requirement | E68: Automate operation through scripts and APIs. | F68: “Operation that can be automated through scripts” | G68: 140, 149 | H68: 142, 151 | I68: ZPA public APIs (API keys with RBAC); OneAPI via the Zscaler Automation Hub | J68: API keys (client ID and secret) give role-scoped access to the public ZPA APIs. OneAPI documentation now lives on the Zscaler Automation Hub (automate.zscaler.com), outside the help centre. | K68: Native | L68: About API Key Management | M68: https://help.zscaler.com/zpa/about-api-key-management | N68: Zscaler Automation Hub — https://automate.zscaler.com/ | O68: [About API Key Management] “An API key is required to access the publicly available set of ZPA APIs. An API key consists of a client ID and a client secret.” [About API Key Management] “Roles for API keys enforce granular role-based access control (RBAC) on all publicly available ZPA API operations.” | P68: [About API Key Management] “If you are subscribed to Authentication Service and have it enabled for your tenant, API keys created in Authentication Service appear on the API Keys page in the Zscaler Admin Console and are read only.” [About API Key Management] “Client secrets are only displayed when the key is first created, and they are not available in the saved configuration.” | Q68: Phase 7 builds in Terraform with the zscaler/zpa provider (README). Open: whether the tenant uses legacy ZPA API keys or OneAPI via Authentication Service decides how automation authenticates — confirm before phase 7. | R68: 2026-10-20
A69: ZT-68 | B69: Getting started | C69: Operations | D69: Guidance | E69: Build runbooks on the vendor's tools for policy updates, diagnostics and agent updates, and triage user-experience problems across WiFi, ISP, backbone, service edge, endpoint, app and DNS. | F69: “Create runbooks that leverage tools provided by the vendor for policy updates, diagnostics, and agent updates.” | G69: 149 | H69: 151 | I69: User Activity Diagnostics; session status codes; dashboards | J69: The Admin Console has User Activity Diagnostics and documented session status codes that name why a request failed (e.g. no policy configured, posture check failed). No policy-simulation tool was found. End-to-end experience triage (Wi-Fi, ISP, backbone) is ZDX — Not ZPA sheet X01. | K69: Partial | L69: Understanding Private Access Session Status Codes | M69: https://help.zscaler.com/zpa/understanding-private-access-session-status-codes | N69: Accessing User Activity Diagnostics — https://help.zscaler.com/zpa/accessing-user-activity-diagnostics What Is Zscaler Private Access? — https://help.zscaler.com/zpa/what-zscaler-private-access | O69: [Understanding Private Access Session Status Codes] “Private Access (ZPA) session status codes appear on the User Activity Diagnostics page. Each table has its own search field and can be sorted by column.” [Understanding Private Access Session Status Codes] “The Private Access service blocked the application request because a policy isn't configured for the requested application. The application request is also blocked when an application segment or a segment group is disabled.” [Understanding Private Access Session Status Codes] “The Private Access service blocked the application request because the device posture check failed.” | P69: [Accessing User Activity Diagnostics] “If you use Custom Range, the start date must be within the last 14 days.” | Q69: Runbooks belong in project/runbooks/ (phase 9). onboarding-failure-triage.spl maps InternalReason to the rejecting component (T-053). | R69: 2026-10-20
A70: ZT-69 | B70: Getting started | C70: Architecture | D70: Guidance | E70: Architect for every exposed connection type — remote and campus users, client, branch and cloud connections — so no path into applications is left outside policy. | F70: “incorporating all exposed connection types (remote/campus, client/branch/cloud connections)” | G70: 146, 149 | H70: 148, 151 | I70: Access-policy client types covering every documented path into Private Access | J70: Client types enumerate the documented paths — Client Connector (incl. VDI and partner), Machine Tunnel, Web Browser, Branch Connector, Cloud Connector, Internet & SaaS Service Edge (Source IP Anchoring), Extranet — and policy can target each. Traffic that never enters one of them (bypass, names matching no segment) is outside ZPA policy and logs. | K70: Native | L70: About Access Policy | M70: https://help.zscaler.com/zpa/about-access-policy | N70: Configuring Defined Application Segments — https://help.zscaler.com/zpa/configuring-defined-application-segments Using Application Segment Multimatch — https://help.zscaler.com/zpa/using-app-segment-multimatch About Machine Groups — https://help.zscaler.com/zpa/about-machine-groups | O70: [About Access Policy] “Client Types: The available client types are Zscaler Client Connector, Client Connector for VDI, Client Connector Partner, Branch Connector, Cloud Connector, Machine Tunnel, Web Browser, Internet & SaaS Service Edge, or Extranet.” [Configuring Defined Application Segments] “If there is no match in this application segment, Zscaler Client Connector bypasses Private Access and sends traffic directly.” | Q70: Paths known to sit outside ZPA policy here: BYPASS rules (T-054), name-less traffic (IP literals, short names), direct internet paths to Azure/AWS apps (current-state.md), and Branch Connector Direct if adopted. | R70: 2026-10-20

Sheet Summary
A1: Coverage summary
A2: Live counts from the Requirements sheet — they update when the Fit column is edited.
A4: Book section | B4: Native | C4: Partial | D4: Other Zscaler product | E4: Dependency | F4: Gap | G4: Not in help centre | H4: Total
A5: Overview of zero trust | B5: =COUNTIFS(Requirements!$B$2:$B$70,$A5,Requirements!$K$2:$K$70,B$4) -> 4 | C5: =COUNTIFS(Requirements!$B$2:$B$70,$A5,Requirements!$K$2:$K$70,C$4) -> 1 | D5: =COUNTIFS(Requirements!$B$2:$B$70,$A5,Requirements!$K$2:$K$70,D$4) -> 0 | E5: =COUNTIFS(Requirements!$B$2:$B$70,$A5,Requirements!$K$2:$K$70,E$4) -> 0 | F5: =COUNTIFS(Requirements!$B$2:$B$70,$A5,Requirements!$K$2:$K$70,F$4) -> 0 | G5: =COUNTIFS(Requirements!$B$2:$B$70,$A5,Requirements!$K$2:$K$70,G$4) -> 0 | H5: =SUM(B5:G5) -> 5
A6: Connecting to the Zero Trust Exchange | B6: =COUNTIFS(Requirements!$B$2:$B$70,$A6,Requirements!$K$2:$K$70,B$4) -> 2 | C6: =COUNTIFS(Requirements!$B$2:$B$70,$A6,Requirements!$K$2:$K$70,C$4) -> 1 | D6: =COUNTIFS(Requirements!$B$2:$B$70,$A6,Requirements!$K$2:$K$70,D$4) -> 1 | E6: =COUNTIFS(Requirements!$B$2:$B$70,$A6,Requirements!$K$2:$K$70,E$4) -> 0 | F6: =COUNTIFS(Requirements!$B$2:$B$70,$A6,Requirements!$K$2:$K$70,F$4) -> 0 | G6: =COUNTIFS(Requirements!$B$2:$B$70,$A6,Requirements!$K$2:$K$70,G$4) -> 0 | H6: =SUM(B6:G6) -> 4
A7: Element 1 — Who is connecting? | B7: =COUNTIFS(Requirements!$B$2:$B$70,$A7,Requirements!$K$2:$K$70,B$4) -> 6 | C7: =COUNTIFS(Requirements!$B$2:$B$70,$A7,Requirements!$K$2:$K$70,C$4) -> 0 | D7: =COUNTIFS(Requirements!$B$2:$B$70,$A7,Requirements!$K$2:$K$70,D$4) -> 2 | E7: =COUNTIFS(Requirements!$B$2:$B$70,$A7,Requirements!$K$2:$K$70,E$4) -> 1 | F7: =COUNTIFS(Requirements!$B$2:$B$70,$A7,Requirements!$K$2:$K$70,F$4) -> 0 | G7: =COUNTIFS(Requirements!$B$2:$B$70,$A7,Requirements!$K$2:$K$70,G$4) -> 0 | H7: =SUM(B7:G7) -> 9
A8: Element 2 — What are the attributes? | B8: =COUNTIFS(Requirements!$B$2:$B$70,$A8,Requirements!$K$2:$K$70,B$4) -> 7 | C8: =COUNTIFS(Requirements!$B$2:$B$70,$A8,Requirements!$K$2:$K$70,C$4) -> 0 | D8: =COUNTIFS(Requirements!$B$2:$B$70,$A8,Requirements!$K$2:$K$70,D$4) -> 0 | E8: =COUNTIFS(Requirements!$B$2:$B$70,$A8,Requirements!$K$2:$K$70,E$4) -> 1 | F8: =COUNTIFS(Requirements!$B$2:$B$70,$A8,Requirements!$K$2:$K$70,F$4) -> 2 | G8: =COUNTIFS(Requirements!$B$2:$B$70,$A8,Requirements!$K$2:$K$70,G$4) -> 0 | H8: =SUM(B8:G8) -> 10
A9: Element 3 — Where is the connection going? | B9: =COUNTIFS(Requirements!$B$2:$B$70,$A9,Requirements!$K$2:$K$70,B$4) -> 11 | C9: =COUNTIFS(Requirements!$B$2:$B$70,$A9,Requirements!$K$2:$K$70,C$4) -> 3 | D9: =COUNTIFS(Requirements!$B$2:$B$70,$A9,Requirements!$K$2:$K$70,D$4) -> 1 | E9: =COUNTIFS(Requirements!$B$2:$B$70,$A9,Requirements!$K$2:$K$70,E$4) -> 0 | F9: =COUNTIFS(Requirements!$B$2:$B$70,$A9,Requirements!$K$2:$K$70,F$4) -> 0 | G9: =COUNTIFS(Requirements!$B$2:$B$70,$A9,Requirements!$K$2:$K$70,G$4) -> 0 | H9: =SUM(B9:G9) -> 15
A10: Element 4 — Assess risk using context | B10: =COUNTIFS(Requirements!$B$2:$B$70,$A10,Requirements!$K$2:$K$70,B$4) -> 0 | C10: =COUNTIFS(Requirements!$B$2:$B$70,$A10,Requirements!$K$2:$K$70,C$4) -> 1 | D10: =COUNTIFS(Requirements!$B$2:$B$70,$A10,Requirements!$K$2:$K$70,D$4) -> 1 | E10: =COUNTIFS(Requirements!$B$2:$B$70,$A10,Requirements!$K$2:$K$70,E$4) -> 0 | F10: =COUNTIFS(Requirements!$B$2:$B$70,$A10,Requirements!$K$2:$K$70,F$4) -> 0 | G10: =COUNTIFS(Requirements!$B$2:$B$70,$A10,Requirements!$K$2:$K$70,G$4) -> 0 | H10: =SUM(B10:G10) -> 2
A11: Element 5 — Prevent compromise | B11: =COUNTIFS(Requirements!$B$2:$B$70,$A11,Requirements!$K$2:$K$70,B$4) -> 5 | C11: =COUNTIFS(Requirements!$B$2:$B$70,$A11,Requirements!$K$2:$K$70,C$4) -> 1 | D11: =COUNTIFS(Requirements!$B$2:$B$70,$A11,Requirements!$K$2:$K$70,D$4) -> 0 | E11: =COUNTIFS(Requirements!$B$2:$B$70,$A11,Requirements!$K$2:$K$70,E$4) -> 0 | F11: =COUNTIFS(Requirements!$B$2:$B$70,$A11,Requirements!$K$2:$K$70,F$4) -> 0 | G11: =COUNTIFS(Requirements!$B$2:$B$70,$A11,Requirements!$K$2:$K$70,G$4) -> 0 | H11: =SUM(B11:G11) -> 6
A12: Element 6 — Prevent data loss | B12: =COUNTIFS(Requirements!$B$2:$B$70,$A12,Requirements!$K$2:$K$70,B$4) -> 0 | C12: =COUNTIFS(Requirements!$B$2:$B$70,$A12,Requirements!$K$2:$K$70,C$4) -> 1 | D12: =COUNTIFS(Requirements!$B$2:$B$70,$A12,Requirements!$K$2:$K$70,D$4) -> 1 | E12: =COUNTIFS(Requirements!$B$2:$B$70,$A12,Requirements!$K$2:$K$70,E$4) -> 0 | F12: =COUNTIFS(Requirements!$B$2:$B$70,$A12,Requirements!$K$2:$K$70,F$4) -> 0 | G12: =COUNTIFS(Requirements!$B$2:$B$70,$A12,Requirements!$K$2:$K$70,G$4) -> 0 | H12: =SUM(B12:G12) -> 2
A13: Element 7 — Enforce policy | B13: =COUNTIFS(Requirements!$B$2:$B$70,$A13,Requirements!$K$2:$K$70,B$4) -> 1 | C13: =COUNTIFS(Requirements!$B$2:$B$70,$A13,Requirements!$K$2:$K$70,C$4) -> 2 | D13: =COUNTIFS(Requirements!$B$2:$B$70,$A13,Requirements!$K$2:$K$70,D$4) -> 1 | E13: =COUNTIFS(Requirements!$B$2:$B$70,$A13,Requirements!$K$2:$K$70,E$4) -> 0 | F13: =COUNTIFS(Requirements!$B$2:$B$70,$A13,Requirements!$K$2:$K$70,F$4) -> 0 | G13: =COUNTIFS(Requirements!$B$2:$B$70,$A13,Requirements!$K$2:$K$70,G$4) -> 0 | H13: =SUM(B13:G13) -> 4
A14: Connecting to the Applications | B14: =COUNTIFS(Requirements!$B$2:$B$70,$A14,Requirements!$K$2:$K$70,B$4) -> 4 | C14: =COUNTIFS(Requirements!$B$2:$B$70,$A14,Requirements!$K$2:$K$70,C$4) -> 0 | D14: =COUNTIFS(Requirements!$B$2:$B$70,$A14,Requirements!$K$2:$K$70,D$4) -> 1 | E14: =COUNTIFS(Requirements!$B$2:$B$70,$A14,Requirements!$K$2:$K$70,E$4) -> 0 | F14: =COUNTIFS(Requirements!$B$2:$B$70,$A14,Requirements!$K$2:$K$70,F$4) -> 0 | G14: =COUNTIFS(Requirements!$B$2:$B$70,$A14,Requirements!$K$2:$K$70,G$4) -> 0 | H14: =SUM(B14:G14) -> 5
A15: Fast, reliable, easy to operate | B15: =COUNTIFS(Requirements!$B$2:$B$70,$A15,Requirements!$K$2:$K$70,B$4) -> 3 | C15: =COUNTIFS(Requirements!$B$2:$B$70,$A15,Requirements!$K$2:$K$70,C$4) -> 1 | D15: =COUNTIFS(Requirements!$B$2:$B$70,$A15,Requirements!$K$2:$K$70,D$4) -> 0 | E15: =COUNTIFS(Requirements!$B$2:$B$70,$A15,Requirements!$K$2:$K$70,E$4) -> 0 | F15: =COUNTIFS(Requirements!$B$2:$B$70,$A15,Requirements!$K$2:$K$70,F$4) -> 0 | G15: =COUNTIFS(Requirements!$B$2:$B$70,$A15,Requirements!$K$2:$K$70,G$4) -> 1 | H15: =SUM(B15:G15) -> 5
A16: Getting started | B16: =COUNTIFS(Requirements!$B$2:$B$70,$A16,Requirements!$K$2:$K$70,B$4) -> 1 | C16: =COUNTIFS(Requirements!$B$2:$B$70,$A16,Requirements!$K$2:$K$70,C$4) -> 1 | D16: =COUNTIFS(Requirements!$B$2:$B$70,$A16,Requirements!$K$2:$K$70,D$4) -> 0 | E16: =COUNTIFS(Requirements!$B$2:$B$70,$A16,Requirements!$K$2:$K$70,E$4) -> 0 | F16: =COUNTIFS(Requirements!$B$2:$B$70,$A16,Requirements!$K$2:$K$70,F$4) -> 0 | G16: =COUNTIFS(Requirements!$B$2:$B$70,$A16,Requirements!$K$2:$K$70,G$4) -> 0 | H16: =SUM(B16:G16) -> 2
A17: Total | B17: =SUM(B5:B16) -> 44 | C17: =SUM(C5:C16) -> 12 | D17: =SUM(D5:D16) -> 8 | E17: =SUM(E5:E16) -> 2 | F17: =SUM(F5:F16) -> 2 | G17: =SUM(G5:G16) -> 1 | H17: =SUM(H5:H16) -> 69
A18: Check: rows on Requirements sheet | H18: =COUNTA(Requirements!$A$2:$A$70) -> 69
A19: Check: rows with a blank or unlisted Fit (should be 0) | H19: =H18-H17 -> 0
A22: Requirement vs guidance
A23: Type | B23: Count
A24: Requirement | B24: =COUNTIF(Requirements!$D$2:$D$70,A24) -> 65
A25: Guidance | B25: =COUNTIF(Requirements!$D$2:$D$70,A25) -> 4

Sheet Not ZPA
A1: ID | B1: Book requirement not met by ZPA | C1: Book pages (printed) | D1: Zscaler product it belongs to | E1: Note
A2: X01 | B2: Monitor end-user experience and diagnose performance (experience score, CloudPath hop analysis) | C2: 15, 141, 146 | D2: Zscaler Digital Experience (ZDX) | E2: Named in the book (p.141). ZT-68 covers the ZPA-side diagnostics.
A3: X02 | B3: Apply internet-layer controls to external apps (e.g. YouTube) and steer internet egress by policy | C3: 61, 127 | D3: Internet & SaaS (ZIA) | E3: The book names ‘Zscaler Internet Access policy’ for egress steering (p.127). ZT-56 covers Source IP Anchoring, which uses ZPA.
A4: X03 | B4: Categorise external apps: predefined/cloud/API-driven definitions, dynamic re-categorisation, newly discovered internet apps, Site Review, suspicious-domain analysis | C4: 62–66 | D4: Internet & SaaS (ZIA) | E4: Internal-app categorisation is ZT-29 to ZT-36.
A5: X04 | B5: One-click Microsoft 365 integration | C5: 62, 140 | D5: Internet & SaaS (ZIA)
A6: X05 | B6: Inline TLS/SSL inspection of internet traffic at scale — TLS 1.3, PFS ciphers, all ports, DNS-tunnelling checks | C6: 82–95 | D6: Internet & SaaS (ZIA) | E6: Private-app inspection is ZT-46 to ZT-51 (AppProtection).
A7: X06 | B7: Secure web gateway, cloud firewall, IPS and cloud sandbox on internet-bound sessions | C7: 94 | D7: Internet & SaaS (ZIA)
A8: X07 | B8: Block the known bad (pattern, signature, destination) with continuous threat-intel updates and the cloud effect | C8: 81 | D8: Internet & SaaS (ZIA)
A9: X08 | B9: Out-of-band (API) scanning of SaaS, IaaS and PaaS for malware and sensitive data at rest; collaboration/oversharing control | C9: 81, 83, 88, 105–108 | D9: CASB / data protection
A10: X09 | B10: Inline DLP for internet, SaaS and email: predefined/custom dictionaries, EDM, IDM, OCR, AIP/MIP labels, ICAP, endpoint DLP | C10: 99–108 | D10: Data protection (Internet & SaaS) | E10: Private-app DLP is ZT-52.
A11: X10 | B11: Inline CASB: cloud-app definitions and risk attributes, sanctioned/unsanctioned app control, file-type controls, block personally encrypted files | C11: 99, 106, 108 | D11: Internet & SaaS (ZIA) / CASB
A12: X11 | B12: SSPM and CNAPP posture: SaaS and IaaS misconfigurations, vulnerabilities, entitlements | C12: 48, 72, 79, 99, 108 | D12: Posture Control (named in the book)
A13: X12 | B13: Company-wide cyber risk assessment: risk by user, industry comparison, risk distribution, riskiest users and locations | C13: 76 | D13: Risk reporting (product not named in the book) | E13: ZPA can consume a user risk score in access policy — ZT-44.
A14: X13 | B14: UEBA: AI/ML and threshold-based user anomaly analytics | C14: 108 | D14: Internet & SaaS (ZIA) | E14: Feeds the user risk score that ZPA can consume — ZT-44.
A15: X14 | B15: IoT/OT device fingerprinting and classification; IoT dashboard | C15: 34, 46, 95, 110 | D15: Internet & SaaS (ZIA) | E15: Book: devices classified by behaviour (p.34).
A16: X15 | B16: Workload-to-internet protection from branches and clouds | C16: 35, 137, 148 | D16: Cloud/Branch Connector with Internet & SaaS (book: ‘ZIA for Workloads’) | E16: Workload-to-private-app is ZT-07.
A17: X16 | B17: Bandwidth control — prioritise business apps, deprioritise social/streaming | C17: 114, 119 | D17: Internet & SaaS (ZIA)
A18: X17 | B18: Quarantine: detonate unknown files in a sandbox, then allow or block | C18: 114, 119, 120 | D18: Internet & SaaS (ZIA) — Cloud Sandbox
A19: X18 | B19: Prevent direct access to sanctioned SaaS from unmanaged devices (book: ‘ID Proxy’) | C19: 44 | D19: Internet & SaaS (ZIA) | E19: Feature name as given in the book.
A20: X19 | B20: Shadow IT report and cloud application dashboard | C20: 110 | D20: Internet & SaaS (ZIA)
A21: X20 | B21: Location-based internet policy (e.g. office user networks may reach the internet, server networks may not) | C21: 40 | D21: Internet & SaaS (ZIA) | E21: Private-app location criteria are ZT-16 and ZT-19.
A22: X21 | B22: Branch appliances and automated SD-WAN tunnel provisioning | C22: 20, 23 | D22: Branch Connector / SD-WAN partners | E22: The ZPA side of site forwarding is ZT-07.
A23: X22 | B23: Single-pass (SSMA) inspection architecture for internet traffic | C23: 93, 138 | D23: Internet & SaaS (ZIA)
A24: X23 | B24: Peering, PeeringDB transparency and diagnostic sites (speedtest.zscaler.com, ip.zscaler.com, Trust portal) | C24: 140 | D24: Platform / commercial | E24: Evidence for ZT-63 rather than a ZPA feature.

Sheet Help articles
A1: Article title | B1: URL | C1: Help-centre section | D1: Cited by (rows, at build) | E1: Verified
A2: Configuring PingFederate as an External IdP | B2: https://help.zscaler.com/authentication-service/configuring-pingfederate-external-idp | C2: Authentication Service | D2: ZT-14 | E2: 2026-10-20
A3: Understanding Step-Up Authentication | B3: https://help.zscaler.com/authentication-service/understanding-step-up-authentication | C3: Authentication Service | D3: ZT-12 | E3: 2026-10-20
A4: Containment Configuration Guide for Private Access | B4: https://help.zscaler.com/deception/containment-configuration-guide-private-access | C4: Deception | D4: ZT-41 | E4: 2026-10-20
A5: Understanding the Zscaler Deception Architecture | B5: https://help.zscaler.com/deception/understanding-zscaler-deception-architecture | C5: Deception | D5: ZT-41 | E5: 2026-10-20
A6: Application Discovery Deployment and Operations Guide | B6: https://help.zscaler.com/zscaler-deployments-operations/application-discovery-deployment-and-operations-guide | C6: Deployments & Operations guides | D6: ZT-29, ZT-32, ZT-33, ZT-34, ZT-35 | E6: 2026-10-20
A7: Configuring Source IP Anchoring | B7: https://help.zscaler.com/zia/configuring-source-ip-anchoring | C7: Internet & SaaS (ZIA) | D7: ZT-56 | E7: 2026-10-20
A8: Understanding Source IP Anchoring | B8: https://help.zscaler.com/zia/understanding-source-ip-anchoring | C8: Internet & SaaS (ZIA) | D8: ZT-56 | E8: 2026-10-20
A9: Understanding User Risk Score | B9: https://help.zscaler.com/zia/understanding-user-risk-score | C9: Internet & SaaS (ZIA) | D9: ZT-21, ZT-44 | E9: 2026-10-20
A10: About AI-Powered Recommendations for Application Segments | B10: https://help.zscaler.com/zpa/about-ai-powered-recommendations-application-segments | C10: Private Access (ZPA) | D10: ZT-36 | E10: 2026-10-20
A11: About API Key Management | B11: https://help.zscaler.com/zpa/about-api-key-management | C11: Private Access (ZPA) | D11: ZT-67 | E11: 2026-10-20
A12: About Access Policy | B12: https://help.zscaler.com/zpa/about-access-policy | C12: Private Access (ZPA) | D12: ZT-03, ZT-04, ZT-07, ZT-15, ZT-16, ZT-17, ZT-19, ZT-20, ZT-23, ZT-24, ZT-28, ZT-30, ZT-41, ZT-54, ZT-55, ZT-69 | E12: 2026-10-20
... A98: Zscaler Config | B98: https://config.zscaler.com/private.zscaler.com/zpa | C98: Zscaler Config (outside the help centre) | D98: ZT-63 | E98: 2026-10-20
